Workbook

Sheet Istruzioni
B2: Diagnosi microimprese — Quanto è solida la tua attività?
B3: 60 minuti per capire punti di forza ed eventuali aree esposte.
B5: Per chi | C5: Per te che gestisci un'attività — qualsiasi attività. Un B&B, una casa vacanze, un ristorante, una bottega, un agriturismo, un negozio, un servizio collegato in maniera diretta o indiretta con il turismo. Non serve esperienza tecnica: se conosci la tua attività, puoi compilarlo.
B6: Cosa fa | C6: Ti dice quanto è solida la tua attività — quanto regge se qualcosa cambia o va male. Non è un esame: è una diagnosi onesta basata sui tuoi dati costruita utilizzando strumenti verificati e progettati su misura per piccole imprese.
B7: Come funziona | C7: (1) 'Prima di iniziare' — 5 minuti, come ti senti tu. (2) 'La tua realtà' — 50-60 minuti, l'analisi vera. (3) 'I risultati numerici' — vengono calcolati automaticamente. (4) 'La relazione personalizzata' - prende in considerazione anche i commenti che aggiungerai, e ti verrà inviata per email.

Sheet Prima di iniziare
B2: PRIMA DI INIZIARE
B3: 5 minuti. Rispondi spontaneamente. Non ci sono risposte giuste o sbagliate e lo scopo di Alva non è giudicare, ma aiutare a comprendere. L'unica cosa che conta è ci racconti la tua attività in maniera trasparente. Più sarai sincero, più la diagnosi sarà accurata e le raccomandazioni operative utili.
A5: 1 | B5: BLOCCO 1: Tu e la tua attività (la tua percezione)
B6: Per ogni domanda, da' un punteggio da 1 (per niente) a 5 (molto).
A7: N. | B7: Domanda | C7: 1-5 | D7: Cosa significa 1 | E7: Cosa significa 3 | F7: Cosa significa 5 | G7: Commenti facoltativi
A8: 1.1 | B8: Senti di avere una storia chiara? Qualcosa che ti rende unico e che i clienti riconoscono? | D8: Non saprei cosa dire di speciale / non ci ho mai pensato | E8: Sento di aver tanto da raccontare ma non riesco a raccontarmi come vorrei | F8: Sì, conosco la mia storia, so quello che faccio e perché e i clienti mi scelgono per quello che sono
A9: 1.2 | B9: Ti senti tranquillo riguardo ai tuoi ricavi? Se un canale di vendita si chiudesse domani, cosa succederebbe? | D9: Non sono tranquillo, dipendo da un unico canale di vendita | E9: Ho diversi canali. Sento di poter fare di più, ma non so come/temo la complessità | F9: Mi sento tranquillo, ho diversi canali e riserve
A10: 1.3 | B10: Quanto ti senti tranquillo sui numeri e, sai quanto guadagni davvero? Sei in regola con pagamenti, tasse, certificazioni? (Ad esempio, HACCP, norme antincendio, sicurezza sul lavoro e altri adempimenti obbligatori) | D10: Non ho idea / non sono sicuro di essere in regola | E10: Ho una conoscenza di base della mia situazione ma non dettagliata | F10: So esattamente quali sono i miei margini, sono a posto con tutto
A11: 1.4 | B11: Se le cose cambiassero improvvisamente (crisi, stagione anomala, nuova legge), ti sentiresti pronto? Sapresti cosa fare? | D11: Ogni imprevisto mette in difficoltà la mia attività | E11: Mi servirebbe del tempo per capire come agire / avrei dubbi sulle decisioni da prendere | F11: Ho piani B, mi adatto in fretta, mi sento preparato per rispondere ai cambiamenti.
A12: 1.5 | B12: Se per qualunque motivo non potessi lavorare per un mese, l'attività andrebbe avanti senza di te? | D12: Si fermerebbe tutto | E12: Continuerebbe con un certo sforzo/dovrei chiedere aiuto esterno | F12: Funzionerebbe quasi normalmente
A13: 1.6 | B13: Ti senti parte di una rete, o lavori da solo? La comunità locale ti vede come una risorsa? | D13: Non ci ho mai pensato / Lavoro completamente isolato | E13: Faccio collaborazioni occasionali ma niente di strutturato | F13: Sono parte di una rete forte, la comunità mi apprezza e viceversa
A14: 1.7 | B14: Senti che stai imparando e migliorando, o ripeti le stesse cose da anni? | D14: Faccio le stesse cose da sempre / Ho appena iniziato | E14: Cerco di tenermi aggiornato ma non sono sicuro di cogliere le opportunità giuste per me | F14: Imparo continuamente, sperimento, mi confronto
B17: BLOCCO 2: Scegli i 3 obiettivi più importanti per te adesso
A18: N. | B18: Obiettivo | C18: 1/2/3 | D18: Perché è importante per te - facoltativo
A19: 2.1 | B19: Riuscire a raccontare meglio cosa mi rende diverso e smettere di competere solo sul prezzo.
A20: 2.2 | B20: Diversificare i ricavi. Non dipendere solo da un canale di vendita o stagione.
A21: 2.3 | B21: Capire i miei numeri davvero (margini, costi, sostenibilità).
A22: 2.4 | B22: Prepararmi agli imprevisti (clima, normative, crisi, aumenti ecc).
A23: 2.5 | B23: Rendere la mia attività meno dipendente da me personalmente.
A24: 2.6 | B24: Collaborare con altre attività. Far parte di una rete. Cercare collaboratori.
A25: 2.7 | B25: Espandermi su mercati o segmenti diversi.
A26: 2.8 | B26: Imparare, migliorare, sperimentare cose nuove.
A27: 2.9 | B27: Rendere più digitale la mia attività e proteggere meglio i dati.
B29: BLOCCO 3: Cosa ti preoccupa di più? (scegline UNA sola)
A30: N. | B30: Preoccupazione | C30: X | D30: Perché ti preoccupa - facoltativo
A31: 3.1 | B31: Non sapere raccontare cosa mi rende diverso e competere solo sul prezzo.
A32: 3.2 | B32: Dipendere troppo da un canale o una stagione.
A33: 3.3 | B33: Non sapere davvero quanto guadagno.
A34: 3.4 | B34: Non essere in regola con qualcosa senza saperlo e scoprirlo troppo tardi.
A35: 3.5 | B35: Non essere preparato per un imprevisto serio (alluvione, pandemia, nuova legge ecc).
A36: 3.6 | B36: Essere così indispensabile per la mia attività, da non poter mai staccare.
A37: 3.7 | B37: Lavorare da solo, senza una rete, senza qualcuno con cui confrontarmi.
A38: 3.8 | B38: Che il mio territorio perda attrattività e io i miei guadagni.
B40: Grazie delle informazioni che hai condiviso. Ora clicca continua per iniziare il questionario vero e proprio.

Sheet La tua realtà
A2: La tua realtà
A3: Per ogni domanda, dai un punteggio da 1 (molto vulnerabile) a 5 (molto forte).
A5: Nome attività
A6: Settore
A7: Località
A8: Data
A10: # | B10: Domanda | C10: Guida ai punteggi | D10: Non ci ho mai pensato | E10: Esempi / come pensarci | F10: 1-5 | G10: Commenti facoltativi
A11: 1. LA TUA VOCE
A12: Sai cosa ti rende diverso? I tuoi clienti lo sanno?
A13: 1.1 | B13: Se ti chiedo perché un cliente dovrebbe scegliere te (non per il prezzo, non per la posizione), cosa risponderesti? | C13: 1 = non saprei cosa rispondere / non ci ho mai pensato 3 = so cosa faccio ma fatico a spiegarlo in modo convincente 5 = ho una storia chiara, la racconto con sicurezza | E13: Non il 'cosa vendi' ma il 'perché lo fai e perché proprio qui'. Se non sai dirlo in 30 secondi, i clienti non lo sanno neanche loro. | H13: =IFERROR(IF(F13="","",F13-1),"")
A14: 1.2 | B14: Quando i clienti ti lasciano una recensione, parlano di qualcosa che solo tu potresti offrire, o potrebbero descrivere qualsiasi altra attività simile? | C14: 1 = parlano solo di prezzo e di posizione 3 = alcuni riconoscono qualcosa di specifico, ma non tutti 5 = le recensioni dicono esattamente perché tornano da me | E14: Rileggi le recensioni o chiedi feedback direttamente ai tuoi clienti. Se potrebbero essere recensioni di un tuo concorrente sei a 1-2. | H14: =IFERROR(IF(F14="","",F14-1),"")
A15: 1.3 | B15: Chi ti trova online e poi viene da te trova la stessa cosa, o si aspettava qualcosa di diverso? | C15: 1 = il modo in cui comunico e presento la mia attività è improvvisato o frammentato / non ci ho mai pensato 3 = il modo in cui comunico e presento la mia attività è abbastanza coerente 5 = chi mi vede online e chi viene da me trova la stessa cosa | E15: Confronta il tuo profilo Instagram con l'esperienza reale: sembrano la stessa attività? | H15: =IFERROR(IF(F15="","",F15-1),"")
B16: MEDIA | F16: =IFERROR(AVERAGE(F13:F15),"") | H16: =IFERROR(AVERAGE(H13:H15),"")
A17: 2. I TUOI RICAVI
A18: Parlaci dei tuoi ricavi. Se un canale si chiude, hai un piano B?
A19: 2.1 | B19: Se il canale che ti porta più clienti chiudesse domani, quanto tempo impiegheresti a rimpiazzare quei ricavi? | C19: 1 = avrei un problema serio, dipendo da un solo canale 3 = ci vorrebbe del tempo ma ho qualche alternativa 5 = ho quattro o più canali attivi, nessuno supera il 40% | D19: x | E19: Non conta quanti canali di vendita hai aperto, ma quanti effettivamente portano clienti. | H19: =IFERROR(IF(F19="","",F19-1),"")
A20: 2.2 | B20: Se la tipologia di clienti che ti porta più ricavi smettesse di venire, quanto sarebbe un problema? | C20: 1 = sarebbe un problema serio, una sola tipologia di cliente copre oltre il 70% dei ricavi 3 = sarebbe difficile ma gestibile, una tipologia sola copre il 40-50% dei ricavi 5 = non mi preoccuperei più di tanto. Nessuna tipologia di clienti supera il 25%, ho un mix reale | D20: x | E20: Famiglie, coppie, business, stranieri ecc. Se una di queste tipologie sparisce, riesci a portare avanti la tua attività senza troppi sforzi? | H20: =IFERROR(IF(F20="","",F20-1),"")
A21: 2.3 | B21: Se i ricavi si azzerassero oggi, quanti mesi di spese fisse potresti coprire? | C21: 1 = meno di 1 mese 3 = 2-3 mesi 5 = 5+ mesi | D21: x | E21: La causa principale di chiusura delle piccole imprese non è la mancanza di clienti, è la cassa che non regge un momento difficile. | H21: =IFERROR(IF(F21="","",F21-1),"")
A22: 2.4 | B22: I tuoi ricavi sono distribuiti nell'anno o concentrati in pochi mesi? | C22: 1 = lavoro meno di 6 mesi l'anno 3 = 6-7 mesi attivi 5 = 10+ mesi con offerta per la bassa stagione | E22: Te lo chiediamo perché i mesi morti costano: affitto, utenze, manutenzione sono spese da sostenere anche quando non lavori. | H22: =IFERROR(IF(F22="","",F22-1),"")
A23: 2.5 | B23: Un cliente che ti trova online può prenotare o acquistare direttamente da te — senza passare da Airbnb, Booking, Shopify o un altro intermediario? | C23: 1 = no, non ho nulla di mio 3 = ho un sito ma senza possibilità di prenotazione o acquisto diretto 5 = sì ho un sito aggiornato e con prenotazione/acquisto diretto | E23: Te lo chiediamo perché serve a valutare il margine di profitto. Ogni prenotazione che passa da una piattaforma ha un costo. Sapere quanto ti costa ogni canale è il primo passo per ridurlo. | H23: =IFERROR(IF(F23="","",F23-1),"")
A24: 2.6 | B24: Su 100 euro di ricavi, quanti arrivano da clienti che comprano direttamente da te, senza passare da piattaforme, portali, marketplace o intermediari? | C24: 1 = meno di 5 euro su 100 arrivano da canali diretti 3 = tra 15 e 25 euro su 100 arrivano da canali diretti 5 = più di 35 euro su 100 arrivano da canali diretti | E24: Te lo chiediamo perché più ricavi diretti hai, più hai controllo sul rapporto con il cliente, sui margini e sulle decisioni commerciali. | H24: =IFERROR(IF(F24="","",F24-1),"")
A25: 2.7 | B25: Se volessi contattare i tuoi clienti domani, per un'offerta, un aggiornamento, per ringraziarli, riusciresti a farlo senza troppi sforzi? Hai un elenco organizzato? | C25: 1 = no / non ci ho mai pensato 3 = ho qualcosa ma non lo uso regolarmente 5 = ho una lista attiva e aggiornata che uso regolarmente per comunicazioni con i clienti | E25: Per esempio, hai un gruppo WhatsApp / mailing list tramite cui raggiungere i tuoi clienti facilmente? | H25: =IFERROR(IF(F25="","",F25-1),"")
B26: MEDIA | F26: =IFERROR(AVERAGE(F19:F25),"") | H26: =IFERROR(AVERAGE(H19:H25),"")
A27: 3. I TUOI MARGINI
A28: Sai davvero quanto guadagni? Sei in regola con tutto?
A29: 3.1 | B29: Alla fine del mese, sai quanto ti rimane davvero dopo aver considerato tutti i costi dell’attività, le tasse previste e il valore del tuo lavoro? | C29: 1 = non l'ho mai calcolato / non ci ho mai pensato 3 = lo so a grandi linee ma non lo controllo ogni mese 5 = lo calcolo ogni mese, includendo costi, tasse previste e valore del mio lavoro | E29: Includi tutti i costi reali dell’attività: affitto, utenze, fornitori, materie prime, commissioni, strumenti, consulenti, trasporti, tasse e contributi. E includi anche il tuo tempo: se non ti paghi, o non consideri il valore del tuo lavoro, il margine che vedi non è reale. | H29: =IFERROR(IF(F29="","",F29-1),"")
A30: 3.2 | B30: Se arrivasse un controllo domani (CIN, sicurezza, GDPR, HACCP, antincendio etc.) saresti tranquillo? | C30: 1 = so che dovrei sistemare delle cose, ci sto lavorando 3 = sono in regola ma non seguo gli aggiornamenti normativi 5 = sono in regola e mi tengo aggiornato quando le regole cambiano | D30: x | E30: Le normative cambiano in fretta. Non sapere ha un costo, spesso più alto di quello che si pensa. | H30: =IFERROR(IF(F30="","",F30-1),"")
A31: 3.3 | B31: Sai qual è il prodotto o servizio su cui guadagni di più, e qual è quello su cui guadagni di meno, con numeri precisi? | C31: 1 = non so / non ci ho mai pensato 3 = saprei rispondere a intuito, ma senza numeri precisi 5 = sì, saprei rispondere con numeri aggiornati e li uso per decidere cosa promuovere, aumentare, ridurre o cambiare | E31: Questa domanda serve a capire se sai dove guadagni davvero. Non tutti i prodotti / servizi hanno lo stesso margine. Alcuni possono vendere tanto ma lasciare poco, perché richiedono molto tempo, hanno costi alti, commissioni, sprechi o consegne costose. Altri possono vendere meno, ma lasciare un margine migliore.
A32: 3.4 | B32: Riesci a dire, senza andare a controllare, quali sono le tue spese più alte questo mese e approssimativamente a quanto ammontano? | C32: 1 = no, vado a sensazione 3 = traccio le spese principali ma non in modo sistematico 5 = ho un sistema per tracciare le spese e rivedo le mie strategie se necessario | E32: Te lo chiediamo perché se non sai dove vanno i soldi, non puoi decidere dove fare tagli o investire. | H32: =IFERROR(IF(F32="","",F32-1),"")
A33: 3.5 | B33: Se domani succedesse un danno serio alla tua attività (allagamento, incendio, furto, danni a un cliente o interruzione forzata) sai se la tua assicurazione coprirebbe le spese principali? | C33: 1 = non ho un’assicurazione / non ci ho mai pensato 3 = ho un’assicurazione di base, ma non sono sicuro di cosa copra davvero 5 = ho una copertura adeguata e so esattamente cosa copre e cosa non copre | E33: Questa domanda serve a capire se, davanti a un danno importante, la tua attività avrebbe una protezione economica oppure se dovresti pagare tutto di tasca tua. Non basta “avere una polizza”: è importante sapere cosa copre davvero. | H33: =IFERROR(IF(F33="","",F33-1),"")
A34: 3.6 | B34: Sei in regola con le ultime scadenze fiscali e contributive (IVA, INPS, imposte sul reddito, acconti)? Hai già messo da parte le somme per le prossime? | C34: 1 = ho scadenze arretrate o non so dove sono 3 = sono in regola ma vado in difficoltà spesso vicino alle scadenze 5 = sono in regola e metto da parte le somme con anticipo | E34: Te lo chiediamo perché le tasse arrivano a rate irregolari — e senza tenerle in conto durante l'anno, le scadenze possono trasformarsi in un problema di liquidità anche quando l'attività va bene.
B35: MEDIA | F35: =IFERROR(AVERAGE(F29:F34),"") | H35: =IFERROR(AVERAGE(H29:H33),"")
A36: 4. LA TUA CAPACITÀ DI ADATTARTI
A37: Quando le cose cambiano, riesci a riadattarti? Guardi verso altri mercati?
A38: 4.1 | B38: Quando noti che i bisogni dei clienti cambiano (per esempio nuove richieste, prodotti meno richiesti o abitudini diverse) riesci ad adattare la tua offerta in modo concreto? | C38: 1 = no, la mia offerta è sostanzialmente identica da anni e non cambia in base ai segnali dei clienti 3 = ogni tanto cambio qualcosa, ma senza un metodo preciso 5 = adatto regolarmente prodotti, servizi, prezzi o modalità di vendita in base a ciò che osservo dai clienti | D38: x | E38: Non serve cambiare tutto in continuazione. Se negli ultimi sei mesi hai introdotto, eliminato o modificato almeno un prodotto / servizio dopo aver osservato il comportamento dei clienti, probabilmente sei già tra 4 e 5. | H38: =IFERROR(IF(F38="","",F38-1),"")
A39: 4.2 | B39: Se da domani un imprevisto ti impedisse di lavorare normalmente per due settimane (per esempio maltempo, guasto, problemi di salute, blocco dei fornitori o chiusura temporanea) sapresti già cosa fare nei primi giorni? | C39: 1 = no, improvviserei / non ci ho mai pensato 3 = ho un’idea generale, ma non ho mai verificato se funzionerebbe 5 = ho un piano chiaro: so chi contattare, quali priorità gestire e quali azioni fare subito | E39: Te lo chiediamo per capire quanto sei preparato a reagire agli imprevisti. Alluvioni, frane, pandemie, ondate di calore, guasti e ritardi dei fornitori non sono solo ipotesi lontane: possono succedere. Avere un piano non significa prevedere tutto, ma sapere almeno quali sono le prime mosse. | H39: =IFERROR(IF(F39="","",F39-1),"")
A40: 4.3 | B40: Se i tuoi clienti locali/abituali smettessero di venire, hai già altri segmenti (da fuori, dall'estero ecc) con cui lavorare? | C40: 1 = i miei clienti sono quasi tutti locali, non ho alternativa 3 = ho qualche cliente che viene da fuori. Sto provando a raggiungere nuovi mercati 5 = ho un mix nazionale e internazionale, con offerta adattata a segmenti diversi | D40: x | E40: Diversificare i mercati non significa smettere di servire i locali, ma significa non dipendere esclusivamente da loro. | G40: Raccontaci brevemente chi sono i tuoi clienti. | H40: =IFERROR(IF(F40="","",F40-1),"")
A41: 4.4 | B41: Se arrivasse un cliente straniero con un problema da risolvere riusciresti ad aiutarlo e a comunicare con successo? | C41: 1 = per niente / penso di non averne bisogno 3 = capisco e mi faccio capire, anche se a fatica 5 = padroneggio la lingua e riesco a rispondere alle esigenze dei clienti stranieri | E41: Non si tratta di essere fluenti. Si tratta di non perdere un cliente per una barriera che si può abbassare. | G41: =IFERROR(IF(F40<=1,"Nota: servi solo clienti locali. Le competenze linguistiche non sono urgenti oggi, ma limitano la crescita futura.",""),"") -> Nota: servi solo clienti locali. Le competenze linguistiche non sono urgenti oggi, ma limitano la crescita futura. | H41: =IFERROR(IF(F41="","",F41-1),"")
B42: MEDIA | F42: =IFERROR(AVERAGE(F38:F41),"") | H42: =IFERROR(AVERAGE(H38:H41),"")
A43: 5. IL TUO SISTEMA
A44: Se ti fermi tu, si ferma tutto?
A45: 5.1 | B45: Se da domani mattina non potessi occuparti della tua attività per un mese, c’è qualcuno (collaboratore, familiare, socio, persona di fiducia ecc) che saprebbe cosa fare e dove trovare le istruzioni principali? | C45: 1 = no, senza di me si fermerebbe tutto 3 = qualcuno potrebbe aiutare, ma con difficoltà e senza istruzioni complete 5 = sì, ci sono persone di riferimento e procedure scritte per gestire le attività principali | E45: Può bastare una rete minima di persone fidate e istruzioni semplici. Per esempio: chi apre e chiude, chi risponde ai clienti, chi gestisce ordini e pagamenti, dove sono password e documenti essenziali. Se tutto è solo nella tua testa, l’attività è più esposta. | H45: =IFERROR(IF(F45="","",F45-1),"")
A46: 5.2 | B46: Se perdessi il telefono domani, quanto tempo ti costerebbe ritrovare le informazioni che ti servono per lavorare? | C46: 1 = sarebbe un problema serio è tutto in testa o sul telefono 3 = uso qualche strumento, ma non mi sento organizzato 5 = uso un sistema digitale strutturato, le informazioni sono accessibili anche in mia assenza | E46: Calendari, liste, app, promemoria — contano tutti. Il punto è se funzionano anche quando non ci sei tu. | H46: =IFERROR(IF(F46="","",F46-1),"")
A47: 5.3 | B47: Se qualcuno ti chiedesse come proteggi i dati dei tuoi clienti, sapresti rispondere con precisione? | C47: 1 = non ci ho mai pensato / non penso sia rilevante per la mia attività 3 = uso sistemi di backup e password, cerco di fare attenzione 5 = ho un sistema preciso e so esattamente come tratto i dati | E47: Un gruppo WhatsApp con i numeri di tutti i clienti visibili a tutti è già una violazione. Non servono sistemi complicati ma serve consapevolezza. | H47: =IFERROR(IF(F47="","",F47-1),"")
A48: 5.4 | B48: Quanto sei attento alla sostenibilità ambientale nella gestione quotidiana? | C48: 1 = non ci ho mai pensato / non penso che sia rilevante per la mia attività 3 = mi adeguo alle normative 5 = rispetto pienamente le normative, propongo soluzioni sostenibili aggiuntive e mi tengo aggiornato | E48: Il 69% dei consumatori italiani è disposto a spendere di più per prodotti/attività sostenibili. Non è solo etica, è posizionamento. | H48: =IFERROR(IF(F48="","",F48-1),"")
A49: 5.5 | B49: C'è qualcosa nella tua struttura che sai che va sistemato ma che rimandi da tempo? | C49: 1 = intervengo solo quando qualcosa si rompe 3 = programmo la manutenzione ma non in modo strutturato 5 = ho piano di manutenzione/ristrutturazione a lungo termine e lo seguo | E49: Te lo chiediamo perché manutenere significa anche risparmiare e ridurre i costi gestione a breve e lungo termine. | H49: =IFERROR(IF(F49="","",F49-1),"")
B50: MEDIA | F50: =IFERROR(AVERAGE(F45:F49),"") | H50: =IFERROR(AVERAGE(H45:H49),"")
A51: 6. LA TUA RETE
A52: Sei solo, o fai parte di una rete?
A53: 6.1 | B53: Hai accordi, anche informali, con altri operatori locali per mandarvi clienti a vicenda? | C53: 1 = nessuno, lavoro da solo 3 = tre–cinque collaborazioni, principalmente informali 5 = faccio parte di una rete strutturata con accordi chiari e reciprocità | E53: Per esempio, hai degli accordi con altre attività locali (ristoranti, bar, piccoli fornitori ecc)? Sponsorizzi altri prodotti/attività nel territorio? | H53: =IFERROR(IF(F53="","",F53-1),"")
A54: 6.2 | B54: Se chiedessi a tre persone del territorio cosa pensano della tua attività, cosa ti aspetti che risponderebbero? | C54: 1 = non ho un rapporto con la comunità locale / non mi sento parte del territorio 3 = la comunità è neutra, non ho né conflitti né legami forti 5 = sono percepito come una risorsa, vengo coinvolto in eventi e progetti locali | D54: x | E54: Te lo chiediamo perché questo conta molto: un buon rapporto con il territorio può portare passaparola, fiducia, clienti ricorrenti, collaborazioni e supporto nei momenti difficili. | G54: Raccontaci della tua attività in relazione alla comunità locale | H54: =IFERROR(IF(F54="","",F54-1),"")
A55: 6.3 | B55: Quando un cliente ti chiede dove mangiare, dove comprare, cosa fare ecc hai una risposta pronta, con nomi precisi? | C55: 1 = no /non ci ho mai pensato 3 = ho qualche consiglio da dare se ci penso 5 = ho un sistema di consigli per diverse esigenze, e gli operatori che consiglio lo sanno | E55: Consigliare un ristoratore e dirgli che lo fai è il gesto più semplice per iniziare una rete. E chi riceve un cliente tende a restituirlo. | H55: =IFERROR(IF(F55="","",F55-1),"")
A56: 6.4 | B56: Sai cosa sta succedendo nel tuo territorio (bandi, progetti, decisioni che potrebbero riguardarti) prima che diventi un problema o un'opportunità persa? | C56: 1 = no, non seguo / non lo ritengo rilevante 3 = mi tengo aggiornato, a volte partecipo 5 = sono attivo, la mia voce conta nella co-progettazione | E56: Chi partecipa è informato in anticipo. Chi non partecipa scopre le cose quando è già troppo tardi. | H56: =IFERROR(IF(F56="","",F56-1),"")
B57: MEDIA | F57: =IFERROR(AVERAGE(F53:F56),"") | H57: =IFERROR(AVERAGE(H53:H56),"")
A58: 7. IL TUO APPRENDIMENTO
A59: Stai imparando e migliorando, o ripeti le stesse cose?
A60: 7.1 | B60: Raccogli e usi le opinioni dei clienti (recensioni, commenti, critiche, domande o osservazioni dirette) per capire cosa migliorare nella tua attività? | C60: 1 = no, non raccolgo o non leggo regolarmente le opinioni dei clienti 3 = le ascolto o le leggo, e ogni tanto ne traggo qualche spunto 5 = raccolgo, osservo e confronto regolarmente i feedback dei clienti, poi li uso per decidere cosa migliorare | E60: Le recensioni, anche quelle negative, spesso contengono informazioni preziose e possono diventare un vantaggio rispetto ai concorrenti. | H60: =IFERROR(IF(F60="","",F60-1),"")
A61: 7.2 | B61: Negli ultimi dodici mesi hai provato qualcosa che non avevi mai fatto prima (anche se non ha funzionato come speravi)? | C61: 1 = no faccio le stesse cose da tempo 3 = ho provato a sperimentare qualcosa di nuovo con risultati parziali 5 = sperimento regolarmente. Anche le talvolta questi esperimenti non funzionano mi danno informazioni utili | E61: Per esempio, hai provato qualcosa di nuovo (una piattaforma, un servizio, un canale di vendita) che non ha funzionato come speravi, ma hai imparato qualcosa di concreto sulla tua attività? Se questo sei tu, sei a 3. | H61: =IFERROR(IF(F61="","",F61-1),"")
A62: 7.3 | B62: Negli ultimi dodici mesi hai imparato qualcosa di nuovo che hai poi usato davvero? | C62: 1 = no / non lo ritengo rilevante 3 = sì, ho seguito un corso strutturato / cerco di ternermi aggiornato 5 = la formazione continua (strutturata o meno) e il confronto attivo sono parte integrante della mia attività. | E62: Non si parla solo di corsi ufficiali o certificati. Può essere anche qualcosa di pratico: imparare a usare meglio i social, tenersi aggiornati su tendenze e cambiamenti, confrontarsi con altri imprenditori, migliorare una procedura ecc. | H62: =IFERROR(IF(F62="","",F62-1),"")
A63: 7.4 | B63: Sai cosa fa meglio di te il tuo competitor più forte? E come usi queste informazioni? | C63: 1 = non guardo mai i competitor / non ci ho mai pensato / non ho competitors 3 = ogni tanto guardo le recensioni/profili pubblici per farmi un'idea 5 = analizzo strategie di vendita, recensioni e sviluppi dei miei competitori in maniera regolare e agisco di conseguenza | E63: Osservi come si presenta il tuo competitore più forte (foto, recensioni, cosa raccontano di sé)? Non per copiarlo, ma per capire cosa ti rende diverso? Se sì, sei tra 4 e 5. Se pensi di non avere competitori diretti, hai mai pensato a quelli indiretti? | H63: =IFERROR(IF(F63="","",F63-1),"")
B64: MEDIA | F64: =IFERROR(AVERAGE(F60:F63),"") | H64: =IFERROR(AVERAGE(H60:H63),"")
B66: IL TUO PUNTEGGIO COMPLESSIVO | F66: =IFERROR(AVERAGE(F16,F26,F35,F42,F50,F57,F64),"") | H66: =IFERROR(AVERAGE(H16,H26,H35,H42,H50,H57,H64),"")
B68: C'è qualcos'altro che vorresti dirci?

Sheet Report_Logic
A1: REPORT LOGIC — Selezione automatica testi da Templates
A2: Non modificare le formule. I testi vengono dai fogli nascosti (1_Apertura...6_Azioni).
A3: A — PUNTEGGI DI RIFERIMENTO
A4: Variabile | B4: Valore | C4: Fonte
A5: Punteggio Voce (1-5) | B5: ='La tua realtà'!F16 | C5: F16
A6: Punteggio Ricavi (1-5) | B6: ='La tua realtà'!F26 | C6: F26
A7: Punteggio Margini (1-5) | B7: ='La tua realtà'!F35 | C7: F35
A8: Punteggio Adattabilità (1-5) | B8: ='La tua realtà'!F42 | C8: F42
A9: Punteggio Sistema (1-5) | B9: ='La tua realtà'!F50 | C9: F50
A10: Punteggio Rete (1-5) | B10: ='La tua realtà'!F57 | C10: F57
A11: Punteggio Apprendimento (1-5) | B11: ='La tua realtà'!F64 | C11: F64
A12: Punteggio Complessivo (1-5) | B12: ='La tua realtà'!F66 | C12: F66
A13: Media CARATTERE (Aree 1,6,7) | B13: =IFERROR(AVERAGE(B5,B10,B11),"") | C13: media F16,F57,F64
A14: Media RISCHIO (Aree 2,3,4,5) | B14: =IFERROR(AVERAGE(B6,B7,B8,B9),"") | C14: media F26,F35,F42,F50
A15: Indicatore Identità | B15: =IFERROR(('La tua realtà'!F13+'La tua realtà'!F14+'La tua realtà'!F15+'La tua realtà'!F54*0.5)/3.5,"") -> 0 | C15: (F13+F14+F15+F54*0.5)/3.5
A16: Indicatore Tenuta dell'attività | B16: =IFERROR(('La tua realtà'!F26+'La tua realtà'!F35)/2,"") | C16: (F26+F35)/2
A17: Indicatore Liquidità | B17: =IFERROR('La tua realtà'!F21,"") -> 0 | C17: F21 = domanda 2.3
A18: Indicatore Resilienza operativa | B18: =IFERROR(('La tua realtà'!F45+'La tua realtà'!F48*0.5+'La tua realtà'!F49+'La tua realtà'!F53+'La tua realtà'!F54+'La tua realtà'!F55*0.5+'La tua realtà'!F56)/6,"") -> 0 | C18: (F45+F48*0.5+F49+F53+F54+F55*0.5+F56)/6
A19: Indicatore Preparazione digitale | B19: =IFERROR(('La tua realtà'!F46+'La tua realtà'!F47+'La tua realtà'!F60*0.5+'La tua realtà'!F23*0.5+'La tua realtà'!F25*0.5)/3.5,"") -> 0 | C19: (F46+F47+F60*0.5+F23*0.5+F25*0.5)/3.5
A20: Indicatore Regole, sicurezza e assicurazioni | B20: =IFERROR(('La tua realtà'!F30+'La tua realtà'!F33+'La tua realtà'!F34+'La tua realtà'!F47)/4,"") -> 0 | C20: (F30+F33+F34+F47)/4
A21: Indicatore Capacità di evoluzione | B21: =IFERROR(('La tua realtà'!F42+'La tua realtà'!F64)/2,"") | C21: (F42+F64)/2
A23: Percezione Voce (1-5) | B23: =IFERROR(IF('Prima di iniziare'!C8="","",'Prima di iniziare'!C8),"") | C23: C8
A24: Percezione Ricavi (1-5) | B24: =IFERROR(IF('Prima di iniziare'!C9="","",'Prima di iniziare'!C9),"") | C24: C10
A25: Percezione Margini (1-5) | B25: =IFERROR(IF('Prima di iniziare'!C10="","",'Prima di iniziare'!C10),"") | C25: C12
A26: Percezione Adattabilità (1-5) | B26: =IFERROR(IF('Prima di iniziare'!C11="","",'Prima di iniziare'!C11),"") | C26: C14
A27: Percezione Sistema (1-5) | B27: =IFERROR(IF('Prima di iniziare'!C12="","",'Prima di iniziare'!C12),"") | C27: C16
A28: Percezione Rete (1-5) | B28: =IFERROR(IF('Prima di iniziare'!C13="","",'Prima di iniziare'!C13),"") | C28: C18
A29: Percezione Apprendimento (1-5) | B29: =IFERROR(IF('Prima di iniziare'!C14="","",'Prima di iniziare'!C14),"") | C29: C20
A31: Logica: P1(Char≥3.5,Ris≥3.5)→P2(Char≥3.5,Ris<2.5)→P3(Char<2.5,Ris≥3.5)→P5(Gen≥3.0,1area<2.0)→P6(Gen<2.5)→P4
A32: B — APERTURA | Profilo selezionato automaticamente
A33: Profilo | B33: Condizione | C33: Testo
A34: Profilo selezionato | B34: =IFERROR(IF(B13="","",IF(AND(B13>=3.5,B14>=3.5),"Profilo 1 — Equilibrio attivo e robusto",IF(AND(B13>=3.5,B14<2.5),"Profilo 2 — Posizionamento forte, basi da consolidare",IF(AND(B13<2.5,B14>=3.5),"Profilo 3 — Basi solide, posizionamento da costruire",IF(AND(B12>=3,COUNTIF(B5:B11,"<2")>=1),"Profilo 5 — Solidita' con punti ciechi",IF(B12<2.5,"Profilo 6 — Fragilita' strutturale","Profilo 4 — In divenire")))))),"") | C34: =IFERROR(IF(B13="","",IF(AND(B13>=3.5,B14>=3.5),'1_Apertura'!D4,IF(AND(B13>=3.5,B14<2.5),'1_Apertura'!D5,IF(AND(B13<2.5,B14>=3.5),'1_Apertura'!D6,IF(AND(B12>=3,COUNTIF(B5:B11,"<2")>=1),'1_Apertura'!D8,IF(B12<2.5,'1_Apertura'!D9,'1_Apertura'!D7)))))),"")
A37: C — LE 7 AREE | Livelli: ≤2.25 Vulnerabile / <3 In costruzione / <3.5 Sufficiente / <4 Solido / ≤5 Forte
A38: Area | B38: Livello attivo | C38: Testo
A39: 1. La tua voce | B39: =IFERROR(IF(B5="","",IF(B5<=2.25,"≤2.25 (Vulnerabile)",IF(B5<3,"<3 (In costruzione)",IF(B5<3.5,"<3.5 (Sufficiente)",IF(B5<4,"<4 (Solido)","≤5 (Forte)"))))),"") | C39: =IFERROR(IF(B5="","",IF(B5<=2,'2_Le7Aree'!C5,IF(B5<=3,'2_Le7Aree'!C6,IF(B5<=4,'2_Le7Aree'!C7,'2_Le7Aree'!C8)))),"")
A40: 2. I tuoi ricavi | B40: =IFERROR(IF(B6="","",IF(B6<=2.25,"≤2.25 (Vulnerabile)",IF(B6<3,"<3 (In costruzione)",IF(B6<3.5,"<3.5 (Sufficiente)",IF(B6<4,"<4 (Solido)","≤5 (Forte)"))))),"") | C40: =IFERROR(IF(B6="","",IF(B6<=2,'2_Le7Aree'!C11,IF(B6<=3,'2_Le7Aree'!C12,IF(B6<=4,'2_Le7Aree'!C13,'2_Le7Aree'!C14)))),"")
A41: 3. I tuoi margini | B41: =IFERROR(IF(B7="","",IF(B7<=2.25,"≤2.25 (Vulnerabile)",IF(B7<3,"<3 (In costruzione)",IF(B7<3.5,"<3.5 (Sufficiente)",IF(B7<4,"<4 (Solido)","≤5 (Forte)"))))),"") | C41: =IFERROR(IF(B7="","",IF(B7<=2,'2_Le7Aree'!C17,IF(B7<=3,'2_Le7Aree'!C18,IF(B7<=4,'2_Le7Aree'!C19,'2_Le7Aree'!C20)))),"")
A42: 4. La tua adattabilità | B42: =IFERROR(IF(B8="","",IF(B8<=2.25,"≤2.25 (Vulnerabile)",IF(B8<3,"<3 (In costruzione)",IF(B8<3.5,"<3.5 (Sufficiente)",IF(B8<4,"<4 (Solido)","≤5 (Forte)"))))),"") | C42: =IFERROR(IF(B8="","",IF(B8<=2,'2_Le7Aree'!C23,IF(B8<=3,'2_Le7Aree'!C24,IF(B8<=4,'2_Le7Aree'!C25,'2_Le7Aree'!C26)))),"")
A43: 5. Il tuo sistema | B43: =IFERROR(IF(B9="","",IF(B9<=2.25,"≤2.25 (Vulnerabile)",IF(B9<3,"<3 (In costruzione)",IF(B9<3.5,"<3.5 (Sufficiente)",IF(B9<4,"<4 (Solido)","≤5 (Forte)"))))),"") | C43: =IFERROR(IF(B9="","",IF(B9<=2,'2_Le7Aree'!C29,IF(B9<=3,'2_Le7Aree'!C30,IF(B9<=4,'2_Le7Aree'!C31,'2_Le7Aree'!C32)))),"")
A44: 6. La tua rete | B44: =IFERROR(IF(B10="","",IF(B10<=2.25,"≤2.25 (Vulnerabile)",IF(B10<3,"<3 (In costruzione)",IF(B10<3.5,"<3.5 (Sufficiente)",IF(B10<4,"<4 (Solido)","≤5 (Forte)"))))),"") | C44: =IFERROR(IF(B10="","",IF(B10<=2,'2_Le7Aree'!C35,IF(B10<=3,'2_Le7Aree'!C36,IF(B10<=4,'2_Le7Aree'!C37,'2_Le7Aree'!C38)))),"")
A45: 7. Il tuo apprendimento | B45: =IFERROR(IF(B11="","",IF(B11<=2.25,"≤2.25 (Vulnerabile)",IF(B11<3,"<3 (In costruzione)",IF(B11<3.5,"<3.5 (Sufficiente)",IF(B11<4,"<4 (Solido)","≤5 (Forte)"))))),"") | C45: =IFERROR(IF(B11="","",IF(B11<=2,'2_Le7Aree'!C41,IF(B11<=3,'2_Le7Aree'!C42,IF(B11<=4,'2_Le7Aree'!C43,'2_Le7Aree'!C44)))),"")
A49: D — INDICATORI DI CONTROLLO | 7 gate non compensativi | Livelli: ≤1.5 Fragile / ≤2.5 Vulnerabile / >2.5 Adeguata / >3.5 Solida
A50: Indicatore | B50: Punteggio | C50: Livello | D50: Gate | E50: Testo
A51: Identità | B51: =B15 -> 0 | C51: =IFERROR(IF(B15="","",IF(B15<=1.5,"≤1.5 (Fragile)",IF(B15<=2.5,"≤2.5 (Vulnerabile)",IF(B15<=3.5,">2.5 (Adeguata)",">3.5 (Solida)")))),"") -> ≤1.5 (Fragile) | D51: =IFERROR(IF(B15="","",IF(B15<=2.5,"WARN","OK")),"") -> WARN | E51: =IFERROR(IF(B15="","",IF(B15<=1.5,'3_Subindici'!C5,IF(B15<=2.5,'3_Subindici'!C6,IF(B15<=3.5,'3_Subindici'!C7,'3_Subindici'!C8)))),"") -> Il tuo posizionamento è sotto la soglia critica. In questo momento chi non ti conosce non riesce a capire perché dovrebbe sceglierti — e in assenza di un motivo chiaro, tende a decidere in base al prezzo o alla posizione. Non si tratta di fare comunicazione: si tratta di capire, prima di tutto internamente, cosa ti rende diverso in modo autentico e riproducibile. Finché questa chiarezza non c'è, ogni investimento in marketing costruisce su fondamenta instabili. Il punto di partenza non è uno strumento — è una conversazione onesta con te stesso su quello che fa davvero la differenza per i tuoi clienti migliori.
A52: Tenuta dell'attività | B52: =B16 | C52: =IFERROR(IF(B16="","",IF(B16<=1.5,"≤1.5 (Fragile)",IF(B16<=2.5,"≤2.5 (Vulnerabile)",IF(B16<=3.5,">2.5 (Adeguata)",">3.5 (Solida)")))),"") | D52: =IFERROR(IF(B16="","",IF(B16<=2,"KO","OK")),"") | E52: =IFERROR(IF(B16="","",IF(B16<=1.5,'3_Subindici'!C10,IF(B16<=2.5,'3_Subindici'!C11,IF(B16<=3.5,'3_Subindici'!C12,'3_Subindici'!C13)))),"")
A53: Liquidità | B53: =B17 -> 0 | C53: =IFERROR(IF(B17="","",IF(B17<=1.5,"≤1.5 (Fragile)",IF(B17<=2.5,"≤2.5 (Vulnerabile)",IF(B17<=3.5,">2.5 (Adeguata)",">3.5 (Solida)")))),"") -> ≤1.5 (Fragile) | D53: =IFERROR(IF(B17="","",IF(B17<=2,"KO","OK")),"") -> KO | E53: =IFERROR(IF(B17="","",IF(B17<=1.5,'3_Subindici'!C15,IF(B17<=2.5,'3_Subindici'!C16,IF(B17<=3.5,'3_Subindici'!C17,'3_Subindici'!C18)))),"") -> Meno di un mese di copertura delle spese fisse. Questo non è un problema di gestione finanziaria — è un'emergenza strutturale. Qualsiasi shock esterno — una settimana lenta, una spesa imprevista, un pagamento in ritardo — può mettere in difficoltà la continuità dell'attività. L'unica priorità adesso è stabilizzare la cassa: ridurre le spese fisse non essenziali, accelerare gli incassi, identificare le voci che si possono posticipare. Ogni altra decisione aspetta che questo indicatore sia fuori dalla zona critica.
A54: Resilienza operativa | B54: =B18 -> 0 | C54: =IFERROR(IF(B18="","",IF(B18<=1.5,"≤1.5 (Fragile)",IF(B18<=2.5,"≤2.5 (Vulnerabile)",IF(B18<=3.5,">2.5 (Adeguata)",">3.5 (Solida)")))),"") -> ≤1.5 (Fragile) | D54: =IFERROR(IF(B18="","",IF(B18<=2.5,"WARN","OK")),"") -> WARN | E54: =IFERROR(IF(B18="","",IF(B18<=1.5,'3_Subindici'!C20,IF(B18<=2.5,'3_Subindici'!C21,IF(B18<=3.5,'3_Subindici'!C22,'3_Subindici'!C23)))),"") -> L'attività dipende interamente da te e opera in isolamento sostanziale. Se ti fermi — anche solo per una settimana — si ferma tutto. E senza una rete nel territorio che possa supportarti, ogni problema si affronta da soli. Queste due fragilità si rinforzano: un sistema fragile senza rete è un'attività che non può permettersi nessuno shock. La priorità è duplice: scrivi il processo più critico della tua attività su un foglio — tre passaggi, in ordine — e contatta tre operatori del territorio questa settimana.
A55: Digital Readiness | B55: =B19 -> 0 | C55: =IFERROR(IF(B19="","",IF(B19<=1.5,"≤1.5 (Fragile)",IF(B19<=2.5,"≤2.5 (Vulnerabile)",IF(B19<=3.5,">2.5 (Adeguata)",">3.5 (Solida)")))),"") -> ≤1.5 (Fragile) | D55: =IFERROR(IF(B19="","",IF(B19<=2.5,"WARN","OK")),"") -> WARN | E55: =IFERROR(IF(B19="","",IF(B19<=1.5,'3_Subindici'!C25,IF(B19<=2.5,'3_Subindici'!C26,IF(B19<=3.5,'3_Subindici'!C27,'3_Subindici'!C28)))),"") -> L'esposizione digitale è sotto la soglia critica. Strumenti inadeguati, dati dei clienti non protetti, assenza di canali diretti e mancato uso delle informazioni disponibili creano una fragilità che si vede poco finché non diventa un problema concreto: una violazione dei dati, una prenotazione persa a causa di un intermediario, una decisione presa senza le informazioni necessarie. Non serve diventare esperti di tecnologia: servono strumenti di base, usati con metodo. L'impatto di un intervento in quest'area è spesso alto e il costo di ingresso è generalmente basso.
A56: Compliance e protezione | B56: =B20 -> 0 | C56: =IFERROR(IF(B20="","",IF(B20<=1.5,"≤1.5 (Fragile)",IF(B20<=2.5,"≤2.5 (Vulnerabile)",IF(B20<=3.5,">2.5 (Adeguata)",">3.5 (Solida)")))),"") -> ≤1.5 (Fragile) | D56: =IFERROR(IF(B20="","",IF(B20<=2,"KO",IF(B20<=3,"WARN","OK"))),"") -> KO | E56: =IFERROR(IF(B20="","",IF(B20<=1.5,'3_Subindici'!C30,IF(B20<=2.5,'3_Subindici'!C31,IF(B20<=3.5,'3_Subindici'!C32,'3_Subindici'!C33)))),"") -> Ci sono gap di compliance significativi su più fronti. Non sapere è rischioso quanto sapere e ignorare: un controllo normativo, un sinistro non coperto o un arretrato fiscale possono generare costi sproporzionati rispetto alle dimensioni dell'attività. La priorità è fare una lista delle criticità note — normative, assicurative, fiscali — e affrontarle in ordine di urgenza. Non tutto va risolto subito, ma tutto deve avere un calendario. Il costo della compliance è fisso e prevedibile; il costo dell'esposizione è imprevedibile e spesso moltiplicatore.
A57: Capacità di evoluzione | B57: =B21 | C57: =IFERROR(IF(B21="","",IF(B21<=1.5,"≤1.5 (Fragile)",IF(B21<=2.5,"≤2.5 (Vulnerabile)",IF(B21<=3.5,">2.5 (Adeguata)",">3.5 (Solida)")))),"") | D57: =IFERROR(IF(B21="","",IF(B21<=2.5,"WARN","OK")),"") | E57: =IFERROR(IF(B21="","",IF(B21<=1.5,'3_Subindici'!C35,IF(B21<=2.5,'3_Subindici'!C36,IF(B21<=3.5,'3_Subindici'!C37,'3_Subindici'!C38)))),"")
A60: E — PERCEZIONE E ANALISI | Attivato se |gap| ≥ 1.5 Gap = Analisi − Percezione. Negativo = ti sentivi meglio. Positivo = stavi sottovalutando.
A61: Area | B61: Gap e direzione | C61: Testo
A62: 1. La tua voce | B62: =IFERROR(IF(OR(B5="",B23=""),"(percezione non compilata)",IF(ABS(B5-B23)<1.5,"Gap < 1.5",IF(B5-B23<0,"Percezione > Analisi (gap="&TEXT(B5-B23,"0.00")&")","Percezione < Analisi (gap="&TEXT(B5-B23,"+0.00")&")"))),"") -> (percezione non compilata) | C62: =IFERROR(IF(OR(B5="",B23=""),"",IF(ABS(B5-B23)<1.5,"—",IF(B5-B23<0,'4_PercAnalisi'!C5,'4_PercAnalisi'!C6))),"")
A63: 2. I tuoi ricavi | B63: =IFERROR(IF(OR(B6="",B24=""),"(percezione non compilata)",IF(ABS(B6-B24)<1.5,"Gap < 1.5",IF(B6-B24<0,"Percezione > Analisi (gap="&TEXT(B6-B24,"0.00")&")","Percezione < Analisi (gap="&TEXT(B6-B24,"+0.00")&")"))),"") -> (percezione non compilata) | C63: =IFERROR(IF(OR(B6="",B24=""),"",IF(ABS(B6-B24)<1.5,"—",IF(B6-B24<0,'4_PercAnalisi'!C8,'4_PercAnalisi'!C9))),"")
A64: 3. I tuoi margini | B64: =IFERROR(IF(OR(B7="",B25=""),"(percezione non compilata)",IF(ABS(B7-B25)<1.5,"Gap < 1.5",IF(B7-B25<0,"Percezione > Analisi (gap="&TEXT(B7-B25,"0.00")&")","Percezione < Analisi (gap="&TEXT(B7-B25,"+0.00")&")"))),"") -> (percezione non compilata) | C64: =IFERROR(IF(OR(B7="",B25=""),"",IF(ABS(B7-B25)<1.5,"—",IF(B7-B25<0,'4_PercAnalisi'!C11,'4_PercAnalisi'!C12))),"")
A65: 4. La tua adattabilità | B65: =IFERROR(IF(OR(B8="",B26=""),"(percezione non compilata)",IF(ABS(B8-B26)<1.5,"Gap < 1.5",IF(B8-B26<0,"Percezione > Analisi (gap="&TEXT(B8-B26,"0.00")&")","Percezione < Analisi (gap="&TEXT(B8-B26,"+0.00")&")"))),"") -> (percezione non compilata) | C65: =IFERROR(IF(OR(B8="",B26=""),"",IF(ABS(B8-B26)<1.5,"—",IF(B8-B26<0,'4_PercAnalisi'!C14,'4_PercAnalisi'!C15))),"")
A66: 5. Il tuo sistema | B66: =IFERROR(IF(OR(B9="",B27=""),"(percezione non compilata)",IF(ABS(B9-B27)<1.5,"Gap < 1.5",IF(B9-B27<0,"Percezione > Analisi (gap="&TEXT(B9-B27,"0.00")&")","Percezione < Analisi (gap="&TEXT(B9-B27,"+0.00")&")"))),"") -> (percezione non compilata) | C66: =IFERROR(IF(OR(B9="",B27=""),"",IF(ABS(B9-B27)<1.5,"—",IF(B9-B27<0,'4_PercAnalisi'!C17,'4_PercAnalisi'!C18))),"")
A67: 6. La tua rete | B67: =IFERROR(IF(OR(B10="",B28=""),"(percezione non compilata)",IF(ABS(B10-B28)<1.5,"Gap < 1.5",IF(B10-B28<0,"Percezione > Analisi (gap="&TEXT(B10-B28,"0.00")&")","Percezione < Analisi (gap="&TEXT(B10-B28,"+0.00")&")"))),"") -> (percezione non compilata) | C67: =IFERROR(IF(OR(B10="",B28=""),"",IF(ABS(B10-B28)<1.5,"—",IF(B10-B28<0,'4_PercAnalisi'!C20,'4_PercAnalisi'!C21))),"")
A68: 7. Il tuo apprendimento | B68: =IFERROR(IF(OR(B11="",B29=""),"(percezione non compilata)",IF(ABS(B11-B29)<1.5,"Gap < 1.5",IF(B11-B29<0,"Percezione > Analisi (gap="&TEXT(B11-B29,"0.00")&")","Percezione < Analisi (gap="&TEXT(B11-B29,"+0.00")&")"))),"") -> (percezione non compilata) | C68: =IFERROR(IF(OR(B11="",B29=""),"",IF(ABS(B11-B29)<1.5,"—",IF(B11-B29<0,'4_PercAnalisi'!C23,'4_PercAnalisi'!C24))),"")
A71: F — AZIONI PRIORITARIE | ★ = corrisponde a obiettivi/preoccupazione dichiarati in Blocchi 2+3
A72: Area | B72: Punteggio | C72: Livello | D72: ★ Priorità | E72: Azione
A73: 1. La tua voce | B73: =B5 | C73: =IFERROR(IF(B5="","",IF(B5<=1.5,"≤1.5 (Critico)",IF(B5<=2.5,"≤2.5 (Attenzione)",IF(B5<=3.5,">2.5 (Solido)",">3.5 (Forte)")))),"") | D73: =IF(OR(ISNUMBER('Prima di iniziare'!C19),'Prima di iniziare'!C31="X",'Prima di iniziare'!C31="x"),"★","") | E73: =IFERROR(IF(B5="","",IF(B5<=1.5,'6_Azioni'!C5,IF(B5<=2.5,'6_Azioni'!C6,IF(B5<=3.5,'6_Azioni'!C7,'6_Azioni'!C8)))),"")
A74: 2. I tuoi ricavi | B74: =B6 | C74: =IFERROR(IF(B6="","",IF(B6<=1.5,"≤1.5 (Critico)",IF(B6<=2.5,"≤2.5 (Attenzione)",IF(B6<=3.5,">2.5 (Solido)",">3.5 (Forte)")))),"") | D74: =IF(OR(ISNUMBER('Prima di iniziare'!C20),'Prima di iniziare'!C32="X",'Prima di iniziare'!C32="x"),"★","") | E74: =IFERROR(IF(B6="","",IF(B6<=1.5,'6_Azioni'!C10,IF(B6<=2.5,'6_Azioni'!C11,IF(B6<=3.5,'6_Azioni'!C12,'6_Azioni'!C13)))),"")
A75: 3. I tuoi margini | B75: =B7 | C75: =IFERROR(IF(B7="","",IF(B7<=1.5,"≤1.5 (Critico)",IF(B7<=2.5,"≤2.5 (Attenzione)",IF(B7<=3.5,">2.5 (Solido)",">3.5 (Forte)")))),"") | D75: =IF(OR(ISNUMBER('Prima di iniziare'!C21),'Prima di iniziare'!C33="X",'Prima di iniziare'!C33="x",'Prima di iniziare'!C34="X",'Prima di iniziare'!C34="x"),"★","") | E75: =IFERROR(IF(B7="","",IF(B7<=1.5,'6_Azioni'!C15,IF(B7<=2.5,'6_Azioni'!C16,IF(B7<=3.5,'6_Azioni'!C17,'6_Azioni'!C18)))),"")
A76: 4. La tua adattabilità | B76: =B8 | C76: =IFERROR(IF(B8="","",IF(B8<=1.5,"≤1.5 (Critico)",IF(B8<=2.5,"≤2.5 (Attenzione)",IF(B8<=3.5,">2.5 (Solido)",">3.5 (Forte)")))),"") | D76: =IF(OR(ISNUMBER('Prima di iniziare'!C22),ISNUMBER('Prima di iniziare'!C25),'Prima di iniziare'!C35="X",'Prima di iniziare'!C35="x"),"★","") | E76: =IFERROR(IF(B8="","",IF(B8<=1.5,'6_Azioni'!C20,IF(B8<=2.5,'6_Azioni'!C21,IF(B8<=3.5,'6_Azioni'!C22,'6_Azioni'!C23)))),"")
A77: 5. Il tuo sistema | B77: =B9 | C77: =IFERROR(IF(B9="","",IF(B9<=1.5,"≤1.5 (Critico)",IF(B9<=2.5,"≤2.5 (Attenzione)",IF(B9<=3.5,">2.5 (Solido)",">3.5 (Forte)")))),"") | D77: =IF(OR(ISNUMBER('Prima di iniziare'!C23),ISNUMBER('Prima di iniziare'!C27),'Prima di iniziare'!C36="X",'Prima di iniziare'!C36="x"),"★","") | E77: =IFERROR(IF(B9="","",IF(B9<=1.5,'6_Azioni'!C25,IF(B9<=2.5,'6_Azioni'!C26,IF(B9<=3.5,'6_Azioni'!C27,'6_Azioni'!C28)))),"")
A78: 6. La tua rete | B78: =B10 | C78: =IFERROR(IF(B10="","",IF(B10<=1.5,"≤1.5 (Critico)",IF(B10<=2.5,"≤2.5 (Attenzione)",IF(B10<=3.5,">2.5 (Solido)",">3.5 (Forte)")))),"") | D78: =IF(OR(ISNUMBER('Prima di iniziare'!C24),'Prima di iniziare'!C37="X",'Prima di iniziare'!C37="x",'Prima di iniziare'!C38="X",'Prima di iniziare'!C38="x"),"★","") | E78: =IFERROR(IF(B10="","",IF(B10<=1.5,'6_Azioni'!C30,IF(B10<=2.5,'6_Azioni'!C31,IF(B10<=3.5,'6_Azioni'!C32,'6_Azioni'!C33)))),"")
A79: 7. Il tuo apprendimento | B79: =B11 | C79: =IFERROR(IF(B11="","",IF(B11<=1.5,"≤1.5 (Critico)",IF(B11<=2.5,"≤2.5 (Attenzione)",IF(B11<=3.5,">2.5 (Solido)",">3.5 (Forte)")))),"") | D79: =IF(OR(ISNUMBER('Prima di iniziare'!C26)),"★","") | E79: =IFERROR(IF(B11="","",IF(B11<=1.5,'6_Azioni'!C35,IF(B11<=2.5,'6_Azioni'!C36,IF(B11<=3.5,'6_Azioni'!C37,'6_Azioni'!C38)))),"")
A82: G — CHIUSURA | Paragrafo finale automatico
A83: Versione | B83: Condizione | C83: Testo
A84: Paragrafo finale contestuale | B84: IF(MediaRischio<3 → rischio, altrimenti carattere) | C84: =IFERROR(IF(B14="","",IF(B14<3,"Le aree su cui intervenire per prime sono quelle di rischio — ricavi, sistema, margini. Non perché le altre non contino, ma perché queste sono le fondamenta: senza di esse, qualsiasi miglioramento altrove costruisce su terreno instabile.","La tua attività ha fondamenta economiche solide. Il lavoro adesso è rafforzare l'identità, il sistema e la capacità di evolversi — gli elementi che trasformano la solidità in antifragilità.")),"")
A85: CTA finale (fissa) | C85: Queste azioni puoi farle da solo — e questo documento ti dice esattamente da dove partire. Se vuoi un percorso su misura — con qualcuno che legge la tua situazione specifica, costruisce un piano concreto e ti accompagna mentre lo realizzi — contattaci. Chi si impegna in un percorso di consulenza personalizzata o in un prodotto Alva Growth entro 14 giorni dal ricevimento di questo report avrà uno sconto del 20% sul prezzo intero.
A88: H — PRIMA DI INIZIARE | Blocchi 2+3 — Obiettivi e preoccupazione dichiarati
A89: Variabile | B89: Valore | C89: Fonte
A90: Obiettivo 1 dichiarato | B90: (non compilato)
A91: Obiettivo 2 dichiarato | B91: (non compilato)
A92: Obiettivo 3 dichiarato | B92: (non compilato)
A93: Preoccupazione principale | B93: (non compilato)
A94: Logica ordinamento azioni | C94: Le aree con ★ nella sezione F corrispondono agli obiettivi/preoccupazione dichiarati e vengono presentate PRIME nel report, prima delle altre aree per punteggio.
A95: NOTA | C95: I fogli 1_Apertura, 2_Le7Aree, 3_Subindici, 4_PercAnalisi, 5_RischioInerzia, 6_Azioni sono nascosti. Per modificare i testi mostra il foglio, modifica col C, nascondilo di nuovo.

Sheet Risultati
A1: 1 · I TUOI RISULTATI
A2: AREA | B2: PUNTEGGIO (1-5) | C2: STATO | D2: DIAGNOSI (dal livello raggiunto)
A3: 1. La tua voce | B3: ='La tua realtà'!F16 | C3: =IFERROR(IF('La tua realtà'!F16="","",IF('La tua realtà'!F16<=2.25,"Vulnerabile",IF('La tua realtà'!F16<3,"In costruzione",IF('La tua realtà'!F16<3.5,"Sufficiente",IF('La tua realtà'!F16<4,"Solido","Forte"))))),"") | D3: =IFERROR(IF('La tua realtà'!F16="","",IF('La tua realtà'!F16<=2.25,'2_Le7Aree'!C5,IF('La tua realtà'!F16<3,'2_Le7Aree'!C6,IF('La tua realtà'!F16<3.5,'2_Le7Aree'!C7,IF('La tua realtà'!F16<4,'2_Le7Aree'!C8,'2_Le7Aree'!C9))))),"")
A4: 2. I tuoi ricavi | B4: ='La tua realtà'!F26 | C4: =IFERROR(IF('La tua realtà'!F26="","",IF('La tua realtà'!F26<=2.25,"Vulnerabile",IF('La tua realtà'!F26<3,"In costruzione",IF('La tua realtà'!F26<3.5,"Sufficiente",IF('La tua realtà'!F26<4,"Solido","Forte"))))),"") | D4: =IFERROR(IF('La tua realtà'!F26="","",IF('La tua realtà'!F26<=2.25,'2_Le7Aree'!C11,IF('La tua realtà'!F26<3,'2_Le7Aree'!C12,IF('La tua realtà'!F26<3.5,'2_Le7Aree'!C13,IF('La tua realtà'!F26<4,'2_Le7Aree'!C14,'2_Le7Aree'!C15))))),"")
A5: 3. I tuoi margini | B5: ='La tua realtà'!F35 | C5: =IFERROR(IF('La tua realtà'!F35="","",IF('La tua realtà'!F35<=2.25,"Vulnerabile",IF('La tua realtà'!F35<3,"In costruzione",IF('La tua realtà'!F35<3.5,"Sufficiente",IF('La tua realtà'!F35<4,"Solido","Forte"))))),"") | D5: =IFERROR(IF('La tua realtà'!F35="","",IF('La tua realtà'!F35<=2.25,'2_Le7Aree'!C17,IF('La tua realtà'!F35<3,'2_Le7Aree'!C18,IF('La tua realtà'!F35<3.5,'2_Le7Aree'!C19,IF('La tua realtà'!F35<4,'2_Le7Aree'!C20,'2_Le7Aree'!C21))))),"")
A6: 4. La tua adattabilità | B6: ='La tua realtà'!F42 | C6: =IFERROR(IF('La tua realtà'!F42="","",IF('La tua realtà'!F42<=2.25,"Vulnerabile",IF('La tua realtà'!F42<3,"In costruzione",IF('La tua realtà'!F42<3.5,"Sufficiente",IF('La tua realtà'!F42<4,"Solido","Forte"))))),"") | D6: =IFERROR(IF('La tua realtà'!F42="","",IF('La tua realtà'!F42<=2.25,'2_Le7Aree'!C23,IF('La tua realtà'!F42<3,'2_Le7Aree'!C24,IF('La tua realtà'!F42<3.5,'2_Le7Aree'!C25,IF('La tua realtà'!F42<4,'2_Le7Aree'!C26,'2_Le7Aree'!C27))))),"")
A7: 5. Il tuo sistema | B7: ='La tua realtà'!F50 | C7: =IFERROR(IF('La tua realtà'!F50="","",IF('La tua realtà'!F50<=2.25,"Vulnerabile",IF('La tua realtà'!F50<3,"In costruzione",IF('La tua realtà'!F50<3.5,"Sufficiente",IF('La tua realtà'!F50<4,"Solido","Forte"))))),"") | D7: =IFERROR(IF('La tua realtà'!F50="","",IF('La tua realtà'!F50<=2.25,'2_Le7Aree'!C29,IF('La tua realtà'!F50<3,'2_Le7Aree'!C30,IF('La tua realtà'!F50<3.5,'2_Le7Aree'!C31,IF('La tua realtà'!F50<4,'2_Le7Aree'!C32,'2_Le7Aree'!C33))))),"")
A8: 6. La tua rete | B8: ='La tua realtà'!F57 | C8: =IFERROR(IF('La tua realtà'!F57="","",IF('La tua realtà'!F57<=2.25,"Vulnerabile",IF('La tua realtà'!F57<3,"In costruzione",IF('La tua realtà'!F57<3.5,"Sufficiente",IF('La tua realtà'!F57<4,"Solido","Forte"))))),"") | D8: =IFERROR(IF('La tua realtà'!F57="","",IF('La tua realtà'!F57<=2.25,'2_Le7Aree'!C35,IF('La tua realtà'!F57<3,'2_Le7Aree'!C36,IF('La tua realtà'!F57<3.5,'2_Le7Aree'!C37,IF('La tua realtà'!F57<4,'2_Le7Aree'!C38,'2_Le7Aree'!C39))))),"")
A9: 7. Il tuo apprendimento | B9: ='La tua realtà'!F64 | C9: =IFERROR(IF('La tua realtà'!F64="","",IF('La tua realtà'!F64<=2.25,"Vulnerabile",IF('La tua realtà'!F64<3,"In costruzione",IF('La tua realtà'!F64<3.5,"Sufficiente",IF('La tua realtà'!F64<4,"Solido","Forte"))))),"") | D9: =IFERROR(IF('La tua realtà'!F64="","",IF('La tua realtà'!F64<=2.25,'2_Le7Aree'!C41,IF('La tua realtà'!F64<3,'2_Le7Aree'!C42,IF('La tua realtà'!F64<3.5,'2_Le7Aree'!C43,IF('La tua realtà'!F64<4,'2_Le7Aree'!C44,'2_Le7Aree'!C45))))),"")
A10: PUNTEGGIO COMPLESSIVO | D10: ='La tua realtà'!F66
A12: 2 · INDICATORI DI CONTROLLO
A13: INDICATORE | B13: Punteggio (1-5) | C13: PRIORITÀ | D13: LIVELLO | E13: TESTO DIAGNOSTICO
A14: Identità | B14: =IFERROR(('La tua realtà'!F13+'La tua realtà'!F14+'La tua realtà'!F15+'La tua realtà'!F54*0.5)/3.5,"") -> 0 | C14: =IF(B14="","",IF(B14<=2.5,"Attenzione","")) -> Attenzione | D14: =IFERROR(IF(B14="","",IF(B14<=1.5,"Fragile",IF(B14<=2.5,"Vulnerabile",IF(B14<=3.5,"Adeguata","Solida")))),"") -> Fragile | E14: =IFERROR(IF(B14="","",IF(B14<=1.5,'3_Subindici'!C5,IF(B14<=2.5,'3_Subindici'!C6,IF(B14<=3.5,'3_Subindici'!C7,'3_Subindici'!C8)))),"") -> Il tuo posizionamento è sotto la soglia critica. In questo momento chi non ti conosce non riesce a capire perché dovrebbe sceglierti — e in assenza di un motivo chiaro, tende a decidere in base al prezzo o alla posizione. Non si tratta di fare comunicazione: si tratta di capire, prima di tutto internamente, cosa ti rende diverso in modo autentico e riproducibile. Finché questa chiarezza non c'è, ogni investimento in marketing costruisce su fondamenta instabili. Il punto di partenza non è uno strumento — è una conversazione onesta con te stesso su quello che fa davvero la differenza per i tuoi clienti migliori.
A15: Sopravvivenza | B15: =IFERROR(('La tua realtà'!F26+'La tua realtà'!F35)/2,"") | C15: =IF(B15="","",IF(B15<=2,"Urgente","")) | D15: =IFERROR(IF(B15="","",IF(B15<=1.5,"Fragile",IF(B15<=2.5,"Vulnerabile",IF(B15<=3.5,"Adeguata","Solida")))),"") | E15: =IFERROR(IF(B15="","",IF(B15<=1.5,'3_Subindici'!C10,IF(B15<=2.5,'3_Subindici'!C11,IF(B15<=3.5,'3_Subindici'!C12,'3_Subindici'!C13)))),"")
A16: Liquidità | B16: =IFERROR('La tua realtà'!F21,"") -> 0 | C16: =IF(B16="","",IF(B16<=2,"Urgente","")) -> Urgente | D16: =IFERROR(IF(B16="","",IF(B16<=1.5,"Fragile",IF(B16<=2.5,"Vulnerabile",IF(B16<=3.5,"Adeguata","Solida")))),"") -> Fragile | E16: =IFERROR(IF(B16="","",IF(B16<=1.5,'3_Subindici'!C15,IF(B16<=2.5,'3_Subindici'!C16,IF(B16<=3.5,'3_Subindici'!C17,'3_Subindici'!C18)))),"") -> Meno di un mese di copertura delle spese fisse. Questo non è un problema di gestione finanziaria — è un'emergenza strutturale. Qualsiasi shock esterno — una settimana lenta, una spesa imprevista, un pagamento in ritardo — può mettere in difficoltà la continuità dell'attività. L'unica priorità adesso è stabilizzare la cassa: ridurre le spese fisse non essenziali, accelerare gli incassi, identificare le voci che si possono posticipare. Ogni altra decisione aspetta che questo indicatore sia fuori dalla zona critica.
A17: Resilienza operativa | B17: =IFERROR(('La tua realtà'!F45+'La tua realtà'!F48*0.5+'La tua realtà'!F49+'La tua realtà'!F53+'La tua realtà'!F54+'La tua realtà'!F55*0.5+'La tua realtà'!F56)/6,"") -> 0 | C17: =IF(B17="","",IF(B17<=2.5,"Attenzione","")) -> Attenzione | D17: =IFERROR(IF(B17="","",IF(B17<=1.5,"Fragile",IF(B17<=2.5,"Vulnerabile",IF(B17<=3.5,"Adeguata","Solida")))),"") -> Fragile | E17: =IFERROR(IF(B17="","",IF(B17<=1.5,'3_Subindici'!C20,IF(B17<=2.5,'3_Subindici'!C21,IF(B17<=3.5,'3_Subindici'!C22,'3_Subindici'!C23)))),"") -> L'attività dipende interamente da te e opera in isolamento sostanziale. Se ti fermi — anche solo per una settimana — si ferma tutto. E senza una rete nel territorio che possa supportarti, ogni problema si affronta da soli. Queste due fragilità si rinforzano: un sistema fragile senza rete è un'attività che non può permettersi nessuno shock. La priorità è duplice: scrivi il processo più critico della tua attività su un foglio — tre passaggi, in ordine — e contatta tre operatori del territorio questa settimana.
A18: Digital Readiness | B18: =IFERROR(('La tua realtà'!F46+'La tua realtà'!F47+'La tua realtà'!F60*0.5+'La tua realtà'!F23*0.5+'La tua realtà'!F25*0.5)/3.5,"") -> 0 | C18: =IF(B18="","",IF(B18<=2.5,"Attenzione","")) -> Attenzione | D18: =IFERROR(IF(B18="","",IF(B18<=1.5,"Fragile",IF(B18<=2.5,"Vulnerabile",IF(B18<=3.5,"Adeguata","Solida")))),"") -> Fragile | E18: =IFERROR(IF(B18="","",IF(B18<=1.5,'3_Subindici'!C25,IF(B18<=2.5,'3_Subindici'!C26,IF(B18<=3.5,'3_Subindici'!C27,'3_Subindici'!C28)))),"") -> L'esposizione digitale è sotto la soglia critica. Strumenti inadeguati, dati dei clienti non protetti, assenza di canali diretti e mancato uso delle informazioni disponibili creano una fragilità che si vede poco finché non diventa un problema concreto: una violazione dei dati, una prenotazione persa a causa di un intermediario, una decisione presa senza le informazioni necessarie. Non serve diventare esperti di tecnologia: servono strumenti di base, usati con metodo. L'impatto di un intervento in quest'area è spesso alto e il costo di ingresso è generalmente basso.
A19: Compliance e protezione | B19: =IFERROR(('La tua realtà'!F30+'La tua realtà'!F33+'La tua realtà'!F34+'La tua realtà'!F47)/4,"") -> 0 | C19: =IF(B19="","",IF(B19<=2,"Urgente",IF(B19<=3,"Attenzione",""))) -> Urgente | D19: =IFERROR(IF(B19="","",IF(B19<=1.5,"Fragile",IF(B19<=2.5,"Vulnerabile",IF(B19<=3.5,"Adeguata","Solida")))),"") -> Fragile | E19: =IFERROR(IF(B19="","",IF(B19<=1.5,'3_Subindici'!C30,IF(B19<=2.5,'3_Subindici'!C31,IF(B19<=3.5,'3_Subindici'!C32,'3_Subindici'!C33)))),"") -> Ci sono gap di compliance significativi su più fronti. Non sapere è rischioso quanto sapere e ignorare: un controllo normativo, un sinistro non coperto o un arretrato fiscale possono generare costi sproporzionati rispetto alle dimensioni dell'attività. La priorità è fare una lista delle criticità note — normative, assicurative, fiscali — e affrontarle in ordine di urgenza. Non tutto va risolto subito, ma tutto deve avere un calendario. Il costo della compliance è fisso e prevedibile; il costo dell'esposizione è imprevedibile e spesso moltiplicatore.
A20: Capacità di evoluzione | B20: =IFERROR(('La tua realtà'!F42+'La tua realtà'!F64)/2,"") | C20: =IF(B20="","",IF(B20<=2.5,"Attenzione","")) | D20: =IFERROR(IF(B20="","",IF(B20<=1.5,"Fragile",IF(B20<=2.5,"Vulnerabile",IF(B20<=3.5,"Adeguata","Solida")))),"") | E20: =IFERROR(IF(B20="","",IF(B20<=1.5,'3_Subindici'!C35,IF(B20<=2.5,'3_Subindici'!C36,IF(B20<=3.5,'3_Subindici'!C37,'3_Subindici'!C38)))),"")
A22: 3 · VARIAZIONE TRA PERCEZIONE E ANALISI · Attivato se |gap| ≥ 1.5
A23: AREA | B23: TU (1-5) | C23: ANALISI (1-5) | D23: GAP | E23: TESTO (se |gap| ≥ 1.5)
A24: 1. La tua voce | B24: =IFERROR(IF('Prima di iniziare'!C8="","(—)",'Prima di iniziare'!C8),"") -> (—) | C24: ='La tua realtà'!F16 | D24: =IFERROR(IF(OR('Prima di iniziare'!C8="",'La tua realtà'!F16=""),"",'La tua realtà'!F16-'Prima di iniziare'!C8),"") | E24: =IFERROR(IF(OR('Prima di iniziare'!C8="",'La tua realtà'!F16=""),"",IF(ABS('La tua realtà'!F16-'Prima di iniziare'!C8)<1.5,"",IF('La tua realtà'!F16-'Prima di iniziare'!C8<0,'4_PercAnalisi'!C5,'4_PercAnalisi'!C6))),"")
A25: 2. I tuoi ricavi | B25: =IFERROR(IF('Prima di iniziare'!C9="","(—)",'Prima di iniziare'!C9),"") -> (—) | C25: ='La tua realtà'!F26 | D25: =IFERROR(IF(OR('Prima di iniziare'!C9="",'La tua realtà'!F26=""),"",'La tua realtà'!F26-'Prima di iniziare'!C9),"") | E25: =IFERROR(IF(OR('Prima di iniziare'!C9="",'La tua realtà'!F26=""),"",IF(ABS('La tua realtà'!F26-'Prima di iniziare'!C9)<1.5,"",IF('La tua realtà'!F26-'Prima di iniziare'!C9<0,'4_PercAnalisi'!C8,'4_PercAnalisi'!C9))),"")
A26: 3. I tuoi margini | B26: =IFERROR(IF('Prima di iniziare'!C10="","(—)",'Prima di iniziare'!C10),"") -> (—) | C26: ='La tua realtà'!F35 | D26: =IFERROR(IF(OR('Prima di iniziare'!C10="",'La tua realtà'!F35=""),"",'La tua realtà'!F35-'Prima di iniziare'!C10),"") | E26: =IFERROR(IF(OR('Prima di iniziare'!C10="",'La tua realtà'!F35=""),"",IF(ABS('La tua realtà'!F35-'Prima di iniziare'!C10)<1.5,"",IF('La tua realtà'!F35-'Prima di iniziare'!C10<0,'4_PercAnalisi'!C11,'4_PercAnalisi'!C12))),"")
A27: 4. La tua adattabilità | B27: =IFERROR(IF('Prima di iniziare'!C11="","(—)",'Prima di iniziare'!C11),"") -> (—) | C27: ='La tua realtà'!F42 | D27: =IFERROR(IF(OR('Prima di iniziare'!C11="",'La tua realtà'!F42=""),"",'La tua realtà'!F42-'Prima di iniziare'!C11),"") | E27: =IFERROR(IF(OR('Prima di iniziare'!C11="",'La tua realtà'!F42=""),"",IF(ABS('La tua realtà'!F42-'Prima di iniziare'!C11)<1.5,"",IF('La tua realtà'!F42-'Prima di iniziare'!C11<0,'4_PercAnalisi'!C14,'4_PercAnalisi'!C15))),"")
A28: 5. Il tuo sistema | B28: =IFERROR(IF('Prima di iniziare'!C12="","(—)",'Prima di iniziare'!C12),"") -> (—) | C28: ='La tua realtà'!F50 | D28: =IFERROR(IF(OR('Prima di iniziare'!C12="",'La tua realtà'!F50=""),"",'La tua realtà'!F50-'Prima di iniziare'!C12),"") | E28: =IFERROR(IF(OR('Prima di iniziare'!C12="",'La tua realtà'!F50=""),"",IF(ABS('La tua realtà'!F50-'Prima di iniziare'!C12)<1.5,"",IF('La tua realtà'!F50-'Prima di iniziare'!C12<0,'4_PercAnalisi'!C17,'4_PercAnalisi'!C18))),"")
A29: 6. La tua rete | B29: =IFERROR(IF('Prima di iniziare'!C13="","(—)",'Prima di iniziare'!C13),"") -> (—) | C29: ='La tua realtà'!F57 | D29: =IFERROR(IF(OR('Prima di iniziare'!C13="",'La tua realtà'!F57=""),"",'La tua realtà'!F57-'Prima di iniziare'!C13),"") | E29: =IFERROR(IF(OR('Prima di iniziare'!C13="",'La tua realtà'!F57=""),"",IF(ABS('La tua realtà'!F57-'Prima di iniziare'!C13)<1.5,"",IF('La tua realtà'!F57-'Prima di iniziare'!C13<0,'4_PercAnalisi'!C20,'4_PercAnalisi'!C21))),"")
A30: 7. Il tuo apprendimento | B30: =IFERROR(IF('Prima di iniziare'!C14="","(—)",'Prima di iniziare'!C14),"") -> (—) | C30: ='La tua realtà'!F64 | D30: =IFERROR(IF(OR('Prima di iniziare'!C14="",'La tua realtà'!F64=""),"",'La tua realtà'!F64-'Prima di iniziare'!C14),"") | E30: =IFERROR(IF(OR('Prima di iniziare'!C14="",'La tua realtà'!F64=""),"",IF(ABS('La tua realtà'!F64-'Prima di iniziare'!C14)<1.5,"",IF('La tua realtà'!F64-'Prima di iniziare'!C14<0,'4_PercAnalisi'!C23,'4_PercAnalisi'!C24))),"")
A32: 4 · COSA RISCHI SE NON INTERVIENI · Soglie: ≤2.25 / <3 / <3.5 / <4 / ≤5
A33: AREA | B33: TESTO (da 5_RischioInerzia, banda attiva)
A34: 1. La tua voce | B34: =IFERROR(IF('La tua realtà'!F16="","",IF('La tua realtà'!F16<=2.25,'5_RischioInerzia'!C4,IF('La tua realtà'!F16<3,'5_RischioInerzia'!C5,IF('La tua realtà'!F16<3.5,'5_RischioInerzia'!C6,IF('La tua realtà'!F16<4,'5_RischioInerzia'!C7,'5_RischioInerzia'!C8))))),"")
A35: 2. I tuoi ricavi | B35: =IFERROR(IF('La tua realtà'!F26="","",IF('La tua realtà'!F26<=2.25,'5_RischioInerzia'!C9,IF('La tua realtà'!F26<3,'5_RischioInerzia'!C10,IF('La tua realtà'!F26<3.5,'5_RischioInerzia'!C11,IF('La tua realtà'!F26<4,'5_RischioInerzia'!C12,'5_RischioInerzia'!C13))))),"")
A36: 3. I tuoi margini | B36: =IFERROR(IF('La tua realtà'!F35="","",IF('La tua realtà'!F35<=2.25,'5_RischioInerzia'!C14,IF('La tua realtà'!F35<3,'5_RischioInerzia'!C15,IF('La tua realtà'!F35<3.5,'5_RischioInerzia'!C16,IF('La tua realtà'!F35<4,'5_RischioInerzia'!C17,'5_RischioInerzia'!C18))))),"")
A37: 4. La tua adattabilità | B37: =IFERROR(IF('La tua realtà'!F42="","",IF('La tua realtà'!F42<=2.25,'5_RischioInerzia'!C19,IF('La tua realtà'!F42<3,'5_RischioInerzia'!C20,IF('La tua realtà'!F42<3.5,'5_RischioInerzia'!C21,IF('La tua realtà'!F42<4,'5_RischioInerzia'!C22,'5_RischioInerzia'!C23))))),"")
A38: 5. Il tuo sistema | B38: =IFERROR(IF('La tua realtà'!F50="","",IF('La tua realtà'!F50<=2.25,'5_RischioInerzia'!C24,IF('La tua realtà'!F50<3,'5_RischioInerzia'!C25,IF('La tua realtà'!F50<3.5,'5_RischioInerzia'!C26,IF('La tua realtà'!F50<4,'5_RischioInerzia'!C27,'5_RischioInerzia'!C28))))),"")
A39: 6. La tua rete | B39: =IFERROR(IF('La tua realtà'!F57="","",IF('La tua realtà'!F57<=2.25,'5_RischioInerzia'!C29,IF('La tua realtà'!F57<3,'5_RischioInerzia'!C30,IF('La tua realtà'!F57<3.5,'5_RischioInerzia'!C31,IF('La tua realtà'!F57<4,'5_RischioInerzia'!C32,'5_RischioInerzia'!C33))))),"")
A40: 7. Il tuo apprendimento | B40: =IFERROR(IF('La tua realtà'!F64="","",IF('La tua realtà'!F64<=2.25,'5_RischioInerzia'!C34,IF('La tua realtà'!F64<3,'5_RischioInerzia'!C35,IF('La tua realtà'!F64<3.5,'5_RischioInerzia'!C36,IF('La tua realtà'!F64<4,'5_RischioInerzia'!C37,'5_RischioInerzia'!C38))))),"")
A42: 5 · AZIONI PRIORITARIE · Ordinate per urgenza · Dalla sezione 6_Azioni
A43: AREA | B43: PUNTEGGIO | C43: PRIORITÀ
A44: 1. La tua voce | B44: ='La tua realtà'!F16 | C44: =IFERROR(IF('La tua realtà'!F16="","",IF('La tua realtà'!F16<=2.25,"Urgente",IF('La tua realtà'!F16<3,"Alta",IF('La tua realtà'!F16<3.5,"Media",IF('La tua realtà'!F16<4,"Bassa","Mantenimento"))))),"") | D44: =IFERROR(IF('La tua realtà'!F16="","",IF('La tua realtà'!F16<=2.25,'6_Azioni'!C4,IF('La tua realtà'!F16<3,'6_Azioni'!C5,IF('La tua realtà'!F16<3.5,'6_Azioni'!C6,IF('La tua realtà'!F16<4,'6_Azioni'!C7,'6_Azioni'!C8))))),"")
A45: 2. I tuoi ricavi | B45: ='La tua realtà'!F26 | C45: =IFERROR(IF('La tua realtà'!F26="","",IF('La tua realtà'!F26<=2.25,"Urgente",IF('La tua realtà'!F26<3,"Alta",IF('La tua realtà'!F26<3.5,"Media",IF('La tua realtà'!F26<4,"Bassa","Mantenimento"))))),"") | D45: =IFERROR(IF('La tua realtà'!F26="","",IF('La tua realtà'!F26<=2.25,'6_Azioni'!C9,IF('La tua realtà'!F26<3,'6_Azioni'!C10,IF('La tua realtà'!F26<3.5,'6_Azioni'!C11,IF('La tua realtà'!F26<4,'6_Azioni'!C12,'6_Azioni'!C13))))),"")
A46: 3. I tuoi margini | B46: ='La tua realtà'!F35 | C46: =IFERROR(IF('La tua realtà'!F35="","",IF('La tua realtà'!F35<=2.25,"Urgente",IF('La tua realtà'!F35<3,"Alta",IF('La tua realtà'!F35<3.5,"Media",IF('La tua realtà'!F35<4,"Bassa","Mantenimento"))))),"") | D46: =IFERROR(IF('La tua realtà'!F35="","",IF('La tua realtà'!F35<=2.25,'6_Azioni'!C14,IF('La tua realtà'!F35<3,'6_Azioni'!C15,IF('La tua realtà'!F35<3.5,'6_Azioni'!C16,IF('La tua realtà'!F35<4,'6_Azioni'!C17,'6_Azioni'!C18))))),"")
A47: 4. La tua adattabilità | B47: ='La tua realtà'!F42 | C47: =IFERROR(IF('La tua realtà'!F42="","",IF('La tua realtà'!F42<=2.25,"Urgente",IF('La tua realtà'!F42<3,"Alta",IF('La tua realtà'!F42<3.5,"Media",IF('La tua realtà'!F42<4,"Bassa","Mantenimento"))))),"") | D47: =IFERROR(IF('La tua realtà'!F42="","",IF('La tua realtà'!F42<=2.25,'6_Azioni'!C19,IF('La tua realtà'!F42<3,'6_Azioni'!C20,IF('La tua realtà'!F42<3.5,'6_Azioni'!C21,IF('La tua realtà'!F42<4,'6_Azioni'!C22,'6_Azioni'!C23))))),"")
A48: 5. Il tuo sistema | B48: ='La tua realtà'!F50 | C48: =IFERROR(IF('La tua realtà'!F50="","",IF('La tua realtà'!F50<=2.25,"Urgente",IF('La tua realtà'!F50<3,"Alta",IF('La tua realtà'!F50<3.5,"Media",IF('La tua realtà'!F50<4,"Bassa","Mantenimento"))))),"") | D48: =IFERROR(IF('La tua realtà'!F50="","",IF('La tua realtà'!F50<=2.25,'6_Azioni'!C24,IF('La tua realtà'!F50<3,'6_Azioni'!C25,IF('La tua realtà'!F50<3.5,'6_Azioni'!C26,IF('La tua realtà'!F50<4,'6_Azioni'!C27,'6_Azioni'!C28))))),"")
A49: 6. La tua rete | B49: ='La tua realtà'!F57 | C49: =IFERROR(IF('La tua realtà'!F57="","",IF('La tua realtà'!F57<=2.25,"Urgente",IF('La tua realtà'!F57<3,"Alta",IF('La tua realtà'!F57<3.5,"Media",IF('La tua realtà'!F57<4,"Bassa","Mantenimento"))))),"") | D49: =IFERROR(IF('La tua realtà'!F57="","",IF('La tua realtà'!F57<=2.25,'6_Azioni'!C29,IF('La tua realtà'!F57<3,'6_Azioni'!C30,IF('La tua realtà'!F57<3.5,'6_Azioni'!C31,IF('La tua realtà'!F57<4,'6_Azioni'!C32,'6_Azioni'!C33))))),"")
A50: 7. Il tuo apprendimento | B50: ='La tua realtà'!F64 | C50: =IFERROR(IF('La tua realtà'!F64="","",IF('La tua realtà'!F64<=2.25,"Urgente",IF('La tua realtà'!F64<3,"Alta",IF('La tua realtà'!F64<3.5,"Media",IF('La tua realtà'!F64<4,"Bassa","Mantenimento"))))),"") | D50: =IFERROR(IF('La tua realtà'!F64="","",IF('La tua realtà'!F64<=2.25,'6_Azioni'!C34,IF('La tua realtà'!F64<3,'6_Azioni'!C35,IF('La tua realtà'!F64<3.5,'6_Azioni'!C36,IF('La tua realtà'!F64<4,'6_Azioni'!C37,'6_Azioni'!C38))))),"")

Sheet Prodotti Alva
A1: Domanda | B1: Cod. prodotto | C1: Trigger | D1: Punteggio soglia | E1: Prodotto suggerito | F1: Messaggio suggerito
A2: 2.5 — Hai un sito/pagina tua? | B2: F2.1 | C2: Punteggio ≤ 2 | D2: ≤2 | E2: alva.travel | F2: Non hai ancora un canale diretto. alva.travel ti dà una pagina tua e visibilità nei territori Alva — senza costruire niente da zero.
A3: 2.6 — % ricavi diretti | B3: F2.2 | C3: Punteggio ≤ 2 | D3: ≤2 | E3: alva.travel | F3: Dipendi quasi completamente dagli intermediari. Con alva.travel puoi iniziare a costruire prenotazioni dirette.
A4: 2.7 — Elenco clienti da ricontattare | B4: F2.3 | C4: Punteggio ≤ 2 | D4: ≤2 | E4: Alva Assistant | F4: Non hai un sistema per ricontattare i tuoi clienti. Alva Assistant ti aiuta a costruire e usare una lista clienti in modo semplice.
A5: 5.2 — Strumenti per gestire l'attività | B5: F5.1 | C5: Punteggio ≤ 2 | D5: ≤2 | E5: Alva Assistant | F5: Gestisci tutto a memoria o su carta. Alva Assistant (Host o Manager) ti aiuta a digitalizzare le operazioni senza complessità.
A6: 5.3 — Dati clienti al sicuro? | B6: F5.4 | C6: Punteggio ≤ 2 | D6: ≤2 | E6: Alva Assistant | F6: I dati dei tuoi clienti non sono protetti. Alva Assistant include backup e gestione sicura dei contatti.
A7: 6.3 — Consigli ai clienti sul territorio | B7: F6.3 | C7: Punteggio ≤ 2 | D7: ≤2 | E7: alva.travel | F7: Non hai ancora un sistema per orientare i tuoi ospiti sul territorio. alva.travel ti dà strumenti per farlo e ti connette agli altri operatori locali.
A8: 6.1 — Collaborazioni con operatori | B8: F6.1 | C8: Punteggio ≤ 2 | D8: ≤2 | E8: alva.travel | F8: Lavori da solo. La rete alva.travel connette operatori locali che collaborano attivamente.
A9: Punteggio F7 < 2.5 (apprendimento debole) | B9: F7 | C9: Media F7 <2.5 | D9: <2.5 | E9: Consulenza personalizzata | F9: Il tuo business ha bisogno di un percorso strutturato. Possiamo aiutarti con una consulenza su misura.
A10: Punteggio F4 < 2 (adattabilità bassa) | B10: F4 | C10: Media F4 <2 | D10: <2 | E10: Consulenza personalizzata | F10: La tua capacità di adattamento è bassa. Un piano personalizzato può aiutarti a costruire resilienza.
A11: Punteggio complessivo < 2 (fragile) | B11: FAI | C11: Punteggio tot <2 | D11: <2 | E11: Consulenza personalizzata | F11: Il tuo punteggio complessivo indica fragilità strutturale. Una consulenza personalizzata può costruire un piano d'azione concreto.
A12: Punteggio complessivo ≥ 2.5 (solido) | B12: FAI | C12: Punteggio tot ≥2.5 | D12: ≥2.5 | E12: RAI Microimprese / Alva Growth Scan | F12: Hai basi solide. Il prossimo passo è misurare il tuo contributo rigenerativo al territorio con il RAI Microimprese.
A13: Indicatore Sopravvivenza KO (<1.5) | B13: F1+F3 | C13: Sopravvivenza <1.5 | D13: <1.5 | E13: Consulenza personalizzata | F13: Emergenza: le fondamenta del business sono a rischio. Una consulenza urgente può aiutarti a stabilizzare la situazione.

Sheet 1_Apertura
A1: SEZIONE 1 — APERTURA | 6 profili parametrici
A2: Profilo | B2: Carattere (media aree 1,6,7) | C2: Rischio (media aree 2,3,4,5) | D2: Testo paragrafo
A3: L'algoritmo calcola le due medie e seleziona il profilo corrispondente. Il testo viene inserito senza titolo come primo paragrafo del report.
A4: Profilo 1 — Sa chi è e regge | B4: ≥ 3.5 | C4: ≥ 3.5 | D4: Hai costruito qualcosa di solido — nel senso più concreto del termine. La tua attività ha un'identità riconoscibile, radici nel territorio, e fondamenta economiche che reggono quando qualcosa cambia. Non è una combinazione comune: molte imprese hanno l'una o l'altra cosa, raramente tutte e due insieme. Quello che emerge dall'analisi non è una lista di problemi da risolvere — è una mappa di quello che vale la pena proteggere e di dove c'è ancora spazio per crescere senza snaturare quello che hai costruito.
A5: Profilo 2 — Sa chi è ma è esposta | B5: ≥ 3.5 | C5: < 2.5 | D5: La tua attività ha un'identità chiara e radici reali nel territorio. Sai chi sei, i clienti ti riconoscono, e quello che fai ha un senso preciso nel contesto in cui operi. Questa è la parte solida. La fragilità sta altrove — nei numeri, nella struttura, nella capacità di reggere uno shock esterno. Chi ha investito molto nell'identità e nelle relazioni spesso ha trascurato le fondamenta operative — non perché non importino, ma perché il tempo non è infinito. Adesso è il momento di lavorarci, partendo da quello che già regge.
A6: Profilo 3 — Regge ma non sa chi è | B6: < 2.5 | C6: ≥ 3.5 | D6: La tua attività è più solida di quanto sembri dall'esterno. I numeri reggono, il sistema funziona, hai una capacità di adattamento reale. Queste sono fondamenta serie, costruite nel tempo con lavoro concreto. Quello che manca non è la solidità — è la visibilità di quella solidità. Chi non ti conosce ancora fatica a capire perché sceglierti. Lavorare sulla voce e sulle radici non significa cambiare quello che sei — significa renderlo riconoscibile anche a chi non ti ha ancora trovato.
A7: Profilo 4 — In costruzione | B7: 2.5–3.4 | C7: 2.5–3.4 | D7: La tua attività è in una fase di costruzione — non nel senso che manca qualcosa di fondamentale, ma nel senso che molte cose sono ancora in divenire. C'è una direzione, c'è un'identità che si sta definendo, ci sono fondamenta che reggono il quotidiano. Ma c'è anche una fragilità diffusa che emerge quando le cose si complicano. Questa è la fase in cui le decisioni pesano di più — perché definiscono la struttura su cui tutto il resto si costruirà. Non serve fare tutto insieme: serve capire da dove iniziare, e procedere con metodo.
A8: Profilo 5 — Forte, un'area critica | B8: ≥ 3.0 gen | C8: 1+ area < 2.0 | D8: Nel complesso la tua attività è solida — con un'eccezione che vale la pena non sottovalutare. C'è un'area specifica che pesa in modo sproporzionato rispetto al resto: non perché le altre siano deboli, ma perché quella fragilità può destabilizzare quello che funziona intorno a lei. Il vantaggio di questa situazione è la chiarezza: non c'è bisogno di rivedere tutto. C'è bisogno di lavorare su un punto preciso, con la consapevolezza che il resto regge e supporta quel lavoro.
A9: Profilo 6 — Fragilità strutturale | B9: < 2.5 gen | C9: < 2.5 gen | D9: L'analisi restituisce un quadro che richiede attenzione su più fronti. Non è una situazione irreversibile — è una situazione in cui le fragilità si sono accumulate nel tempo senza che ci fosse mai il momento giusto per affrontarle una per una. Il rischio principale non è un singolo problema: è la combinazione di più fragilità che si rinforzano a vicenda. Affrontarle tutte insieme non è possibile né necessario. Quello che serve è identificare il punto di partenza giusto — quello che, risolto, alleggerisce anche il peso degli altri — e iniziare da lì con metodo.

Sheet 2_Le7Aree
A1: SEZIONE 2 — LE 7 AREE | 7 aree × 5 livelli | Scala 1–5
A2: Area | B2: Livello (media 1–5) | C2: Testo paragrafo
A3: Livelli: ≤2.25 (Vulnerabile) | <3.00 (In costruzione) | <3.50 (Sufficiente) | <4.00 (Solido) | ≤5.00 (Forte)
A4: 1. La tua voce
A5: 1. La tua voce | B5: ≤2.25 | C5: Chi non ti conosce ancora fatica a capire perché sceglierti rispetto a un'alternativa simile. Non è una questione di qualità — è una questione di visibilità di quella qualità. Chi non sa perché sceglierti tende a decidere in base al prezzo o alla posizione: i due criteri su cui è più difficile competere per una piccola impresa. La tua storia esiste — non è ancora stata trovata e raccontata nel modo che le appartiene.
A6: 1. La tua voce | B6: <3.00 | C6: Hai qualcosa da raccontare, ma non arriva ancora con la coerenza che meriterebbe. Chi entra in contatto con la tua attività percepisce che c'è qualcosa di autentico, ma fatica a capire esattamente cosa ti distingue. I clienti giusti arrivano, spesso per caso più che per scelta deliberata. Non serve una strategia di comunicazione complessa: serve chiarire internamente cosa ti rende diverso e portarlo fuori con più coerenza.
A7: 1. La tua voce | B7: <3.50 | C7: Sai chi sei e riesci a dirlo in modo abbastanza chiaro. I tuoi clienti capiscono cosa offri e perché sceglierti. Non è ancora la voce forte e riconoscibile che lavora per te anche quando non ci sei — ma è una base solida su cui costruire. Il lavoro adesso è la coerenza: stesso messaggio su ogni canale, stesso tono in ogni interazione.
A8: 1. La tua voce | B8: <4.00 | C8: Sai chi sei e lo comunichi con precisione. I tuoi clienti ti scelgono per quello che sei — non solo per dove sei o per quanto costi. Questa chiarezza è rara e vale più di qualsiasi strumento di marketing. L'unica cosa su cui restare attenti è la coerenza nel tempo: una voce chiara può diventare inconsistente gradualmente se non viene curata e aggiornata quando l'offerta evolve.
A9: 1. La tua voce | B9: ≤5.00 | C9: Sai chi sei e lo comunichi con precisione in ogni punto di contatto. I tuoi clienti ti scelgono consapevolmente e sanno spiegarlo. Questo posizionamento ti mette in una condizione strutturalmente vantaggiosa: non competi solo sul prezzo o sulla posizione, ma sul valore che solo tu puoi offrire. Continua a coltivare questa voce, tienila coerente e documentala in modo che regga anche quando l'attività cresce o cambia.
A10: 2. I tuoi ricavi
A11: 2. I tuoi ricavi | B11: ≤2.25 | C11: I tuoi ricavi hanno una fragilità che richiede attenzione prioritaria. La causa più comune di chiusura delle piccole imprese non è la mancanza di clienti — è la liquidità. Se i ricavi si azzerassero oggi, quanto potresti andare avanti? La dipendenza da un canale solo, da un periodo dell'anno solo, o l'assenza di riserve: ognuno è gestibile da solo. Insieme diventano un rischio strutturale.
A12: 2. I tuoi ricavi | B12: <3.00 | C12: C'è qualcosa che funziona nei tuoi ricavi, ma c'è anche un'esposizione che probabilmente non percepisci nella sua interezza. Non è una crisi: è una fragilità silenziosa che si manifesta quando arriva uno shock esterno. Non serve rivoluzionare tutto — serve identificare il punto di maggiore concentrazione e costruire almeno un'alternativa concreta, che sia un secondo canale, un periodo dell'anno che oggi non copri, o una riserva minima.
A13: 2. I tuoi ricavi | B13: <3.50 | C13: Hai una base di ricavi che regge il quotidiano e tiene discretamente agli shock stagionali. Non c'è ancora la diversificazione piena che permetterebbe di affrontare una crisi prolungata senza pressione, ma la struttura funziona. Il lavoro adesso è consolidarla: ridurre la concentrazione nei mesi o canali più forti e costruire prevedibilità sui flussi.
A14: 2. I tuoi ricavi | B14: <4.00 | C14: I tuoi ricavi sono costruiti su basi solide. Hai diversificato abbastanza da reggere un momento difficile senza andare in crisi. Resta attento alla stagionalità e all'evoluzione dei canali: anche quando i ricavi reggono bene, la dipendenza da pochi mesi o da pochi intermediari crea vulnerabilità che non si vedono finché non si manifestano.
A15: 2. I tuoi ricavi | B15: ≤5.00 | C15: I tuoi ricavi sono solidi, diversificati e distribuiti nell'anno. Hai più canali attivi, riserve adeguate e una struttura che ti protegge dagli shock stagionali e dalle variazioni di singoli canali. Hai già fatto il lavoro più difficile — costruire resilienza prima che fosse necessaria. Il passo successivo è ottimizzare il mix e sviluppare flussi ricorrenti che non dipendano dall'acquisizione continua di nuovi clienti.
A16: 3. I tuoi margini
A17: 3. I tuoi margini | B17: ≤2.25 | C17: C'è una zona d'ombra sui tuoi numeri che vale la pena illuminare. Non sapere con precisione quanto resta dopo tutte le spese — incluso il valore del tuo lavoro — significa prendere decisioni importanti senza le informazioni che servono. Il rischio concreto è duplice: lavorare in perdita senza saperlo, e trovarsi impreparati davanti a un cambiamento normativo o fiscale.
A18: 3. I tuoi margini | B18: <3.00 | C18: Hai una conoscenza parziale dei tuoi numeri. Il rischio specifico è lavorare a un margine più basso di quello che percepisci — non perché i ricavi manchino, ma perché alcune spese non vengono conteggiate o vengono sottostimate. Il costo del proprio tempo è il primo a sparire dal calcolo: se non lo includi, il margine che vedi non è quello reale.
A19: 3. I tuoi margini | B19: <3.50 | C19: Tieni i tuoi numeri abbastanza sotto controllo da sapere dove stai. Non hai ancora la granularità che permetterebbe di ottimizzare il pricing per linea o per cliente, ma sai quando qualcosa non torna e riesci a correggere. Il passo successivo è strutturare il tracciamento in modo da avere una lettura mensile precisa, non solo una sensazione.
A20: 3. I tuoi margini | B20: <4.00 | C20: Sai dove vanno i soldi. Conosci il margine reale, tieni traccia delle spese, sei sostanzialmente in regola. Questo è più raro di quanto sembri tra le micro-imprese. La solidità su quest'area ti permette di prendere decisioni consapevoli — su dove tagliare, dove investire, dove il lavoro non si traduce ancora in margine adeguato.
A21: 3. I tuoi margini | B21: ≤5.00 | C21: Hai una visione chiara e precisa dei tuoi numeri. Conosci il margine reale per linea e per cliente, la compliance è a posto e usi i dati per prendere decisioni. Questo ti dà un vantaggio strutturale rispetto a chi va a sensazione. Il passo successivo è usare questa chiarezza per ottimizzare il pricing, migliorare il mix di offerta e reinvestire in crescita con piena consapevolezza del rendimento atteso.
A22: 4. La tua adattabilità
A23: 4. La tua adattabilità | B23: ≤2.25 | C23: La tua attività è esposta ai cambiamenti più di quanto sarebbe necessario. Non perché manchino le competenze — ma perché in questo momento non ci sono ancora gli strumenti per intercettare i segnali in anticipo e rispondere con metodo. La dipendenza da un mercato solo e l'assenza di un piano per gli imprevisti sono i due rischi più concreti da affrontare.
A24: 4. La tua adattabilità | B24: <3.00 | C24: C'è una capacità di adattamento nella tua attività, ma tende ad attivarsi quando la pressione è già alta, non prima. Rispondi ai cambiamenti più che anticiparli. Il problema più comune a questo livello non è la mancanza di flessibilità — è la mancanza di struttura per guardarsi intorno con regolarità. Anche un'ora alla settimana dedicata a osservare cosa cambia può fare una differenza concreta.
A25: 4. La tua adattabilità | B25: <3.50 | C25: Riesci ad adattarti quando è necessario e hai qualche offerta per segmenti o periodi diversi da quelli principali. Non è ancora la diversificazione strutturata che permette di attraversare uno shock senza perdita significativa, ma la flessibilità c'è. Il lavoro adesso è renderla meno dipendente dal momento di pressione e più parte di come l'attività funziona ordinariamente.
A26: 4. La tua adattabilità | B26: <4.00 | C26: Quando le cose cambiano, cambi anche tu. Hai dimostrato di saper ascoltare i clienti e tradurre quello che senti in decisioni concrete. Questa capacità è uno degli asset più difficili da costruire. Continua a coltivare la diversità dei mercati e mantieni attivi più segmenti in parallelo: è quello che trasforma una buona capacità di adattamento in resilienza strutturale.
A27: 4. La tua adattabilità | B27: ≤5.00 | C27: Hai una capacità di adattamento attiva e strutturata. Anticipi i cambiamenti, servi mercati diversi, hai piani per gli imprevisti. Sei nella posizione in cui la volatilità del contesto non è solo un rischio — può diventare un vantaggio competitivo rispetto a chi non è attrezzato. Il lavoro adesso è mantenere la disciplina dell'osservazione sistematica anche quando tutto va bene.
A28: 5. Il tuo sistema
A29: 5. Il tuo sistema | B29: ≤2.25 | C29: In questo momento la tua attività e la tua presenza coincidono quasi completamente. Se ti fermi, si ferma tutto. Questo non è un problema di efficienza: è un rischio strutturale. Le tre aree più critiche a questo livello sono la dipendenza personale (nessuno sa fare quello che sai fare tu), la gestione e protezione dei dati, e l'assenza di procedure scritte per i processi più critici.
A30: 5. Il tuo sistema | B30: <3.00 | C30: La tua attività funziona — ma funziona soprattutto perché ci sei tu. Se ti fermassi per due settimane, qualcosa si incepperebbe. Il sistema regge il ritmo normale, ma non regge gli imprevisti. Ogni piccolo passo verso la delega — scrivere una procedura, formare qualcuno su un compito critico, fare un backup automatico — riduce la fragilità complessiva in modo significativo.
A31: 5. Il tuo sistema | B31: <3.50 | C31: Hai le basi di un sistema che può funzionare anche senza di te per periodi brevi. Ci sono alcune procedure, alcuni strumenti, qualcuno che conosce almeno parte del funzionamento. Non è ancora abbastanza per un'assenza prolungata o un imprevisto serio, ma la direzione è quella giusta. Il lavoro è completare la copertura: identificare le lacune critiche e colmarle una alla volta.
A32: 5. Il tuo sistema | B32: <4.00 | C32: La tua attività non dipende solo da te. Hai strumenti che funzionano, procedure che reggono anche quando non ci sei, e una gestione dei dati che non ti espone a rischi inutili. Questo è il tipo di solidità che non si vede dall'esterno ma che si sente ogni volta che qualcosa va storto. Vale la pena continuare a investirci anche quando non sembra urgente.
A33: 5. Il tuo sistema | B33: ≤5.00 | C33: Hai un sistema solido e delegabile. Le procedure ci sono, gli strumenti funzionano, i dati sono protetti. Sei nella posizione in cui un'assenza improvvisa non mette a rischio l'attività. Il passo successivo è evolvere verso un sistema che non solo regge senza di te, ma che raccoglie dati, segnala anomalie e si aggiorna in modo strutturato nel tempo.
A34: 6. Le tue radici
A35: 6. Le tue radici | B35: ≤2.25 | C35: In questo momento stai lavorando in modo sostanzialmente isolato. L'isolamento ha un costo che non sempre si vede: opportunità che non arrivano, problemi che si affrontano da soli, risorse del territorio che non vengono intercettate. Per una piccola impresa in un'area come la tua, la rete locale non è un optional — è un moltiplicatore. Un referral attivo con tre operatori vicini può valere più di un anno di campagne promozionali.
A36: 6. Le tue radici | B36: <3.00 | C36: Hai alcune connessioni con il territorio, ma non ancora una rete strutturata su cui poter contare quando serve. Le relazioni che esistono restano informali e asimmetriche: si manda qualche cliente ogni tanto, si collabora se capita. Rendere queste relazioni un po' più strutturate — anche solo con un accordo verbale chiaro su chi manda cosa a chi — cambia il valore che quella rete può generare.
A37: 6. Le tue radici | B37: <3.50 | C37: Sei presente nel territorio e hai relazioni che generano un certo valore. Non è ancora la rete densa e reciproca che funziona anche quando non sei tu a spingere, ma sei riconoscibile e ci sono collaborazioni attive. Il lavoro adesso è consolidare: da relazioni informali ad accordi espliciti, da presenza occasionale a presenza riconoscibile.
A38: 6. Le tue radici | B38: <4.00 | C38: Sei parte del territorio in cui lavori — non solo geograficamente, ma nella sostanza. Hai relazioni con altri operatori, la comunità ti riconosce. Questo tipo di radicamento è uno degli asset più difficili da costruire e più difficili da replicare. Le reti si mantengono con la presenza e la reciprocità: vale la pena continuare a investirci in modo attivo.
A39: 6. Le tue radici | B39: ≤5.00 | C39: Sei un punto di riferimento del territorio. Le relazioni che hai costruito generano valore in modo sempre più autonomo — clienti che arrivano per referral, informazioni che circolano, opportunità che vengono a te prima che tu le cerchi. Il passo successivo è strutturare questo vantaggio in modo che sia ancora più solido e meno dipendente dalla tua presenza diretta.
A40: 7. Il tuo apprendimento
A41: 7. Il tuo apprendimento | B41: ≤2.25 | C41: In questo momento la tua attività si muove principalmente sulla base dell'esperienza accumulata — che è una risorsa preziosa, ma che da sola non basta a intercettare quello che sta cambiando intorno. Chi non ha un canale attivo per raccogliere segnali tende a scoprirli in ritardo, quando il margine di manovra si è già ridotto.
A42: 7. Il tuo apprendimento | B42: <3.00 | C42: C'è una curiosità nella tua attività, ma l'apprendimento tende a essere episodico più che sistematico. Succede quando c'è tempo, quando capita un'occasione. Anche una sola abitudine piccola e regolare — leggere le ultime recensioni una volta al mese, visitare un competitor ogni trimestre — cambia la qualità delle decisioni nel tempo senza richiedere un investimento significativo.
A43: 7. Il tuo apprendimento | B43: <3.50 | C43: Impari in modo abbastanza regolare e le informazioni che raccogli influenzano le tue decisioni. Non è ancora un ciclo strutturato in cui ogni osservazione produce un'azione misurabile, ma la curiosità c'è e si traduce in cambiamenti concreti. Il lavoro adesso è rendere questo processo più deliberato: tracciare quello che sperimenti e misurare cosa cambia.
A44: 7. Il tuo apprendimento | B44: <4.00 | C44: Stai imparando in modo attivo, non per caso. Ascolti i clienti con metodo, ti confronti con chi fa cose simili, sperimenti senza aspettare che sia strettamente necessario. L'unica cosa su cui restare attenti è la qualità dell'apprendimento rispetto alla quantità: un corso seguito o un evento partecipato vale se produce almeno un'azione diversa da prima.
A45: 7. Il tuo apprendimento | B45: ≤5.00 | C45: Hai una cultura dell'apprendimento attiva e strutturata. Ogni ciclo cambia qualcosa in base a quello che hai osservato, testato, imparato. Sei nella posizione in cui non stai solo reagendo al mercato — stai contribuendo a interpretarlo. Il passo successivo è rendere questo processo ancora più sistematico e condividerlo con chi lavora con te.

Sheet 3_Subindici
A1: SEZIONE 3 — SUB-INDICI | 7 sub-indici × 4 livelli | Scala 1–5
A2: Sub-indice | B2: Livello | C2: Testo paragrafo
A3: Livelli: ≤1.5 (Fragile) ≤2.5 (Vulnerabile) >2.5 (Adeguata) >3.5 (Solida)
A4: Identità
A5: Identità | B5: ≤1.5 (Fragile) | C5: Il tuo posizionamento è sotto la soglia critica. In questo momento chi non ti conosce non riesce a capire perché dovrebbe sceglierti — e in assenza di un motivo chiaro, tende a decidere in base al prezzo o alla posizione. Non si tratta di fare comunicazione: si tratta di capire, prima di tutto internamente, cosa ti rende diverso in modo autentico e riproducibile. Finché questa chiarezza non c'è, ogni investimento in marketing costruisce su fondamenta instabili. Il punto di partenza non è uno strumento — è una conversazione onesta con te stesso su quello che fa davvero la differenza per i tuoi clienti migliori.
A6: Identità | B6: ≤2.5 (Vulnerabile) | C6: Il tuo posizionamento è parziale: c'è qualcosa da raccontare, ma non emerge ancora con la coerenza e la chiarezza che servono. I clienti giusti arrivano, ma spesso per caso o per canali che non controlli. L'identità esiste — non è ancora stata trovata e comunicata nel modo che le appartiene. Non serve costruire qualcosa di nuovo da zero: serve mettere a fuoco quello che già c'è e renderlo riconoscibile in modo coerente su ogni punto di contatto, dal sito alle recensioni, dall'esperienza fisica alla risposta ai messaggi.
A7: Identità | B7: >2.5 (Adeguata) | C7: Il tuo posizionamento è solido. Sai chi sei, i tuoi clienti lo riconoscono e la tua storia viene comunicata con una certa coerenza. Questo è un asset reale: un'identità chiara riduce la pressione sul prezzo, attrae i clienti giusti e genera fedeltà nel tempo. Il rischio a questo livello è la deriva graduale — un'identità che non viene curata con regolarità tende ad affievolirsi quando l'attività cresce o cambia. Vale la pena presidiare la coerenza su tutti i punti di contatto e assicurarsi che chi lavora con te sappia raccontare la stessa storia.
A8: Identità | B8: >3.5 (Solida) | C8: Il tuo posizionamento è forte e riconoscibile. I clienti ti scelgono consapevolmente e sanno spiegarlo: non competi sul prezzo perché il valore che offri è visibile e percepito come unico. Questa è una delle condizioni più difficili da costruire e più facili da perdere se non viene curata. Il lavoro adesso è documentare questo posizionamento in modo che regga nel tempo, si trasferisca a chi lavora con te e possa evolvere senza perdere coerenza. Considera di costruire un archivio di testimonianze e materiali che raccontino la tua storia anche in tua assenza.
A9: Sopravvivenza
A10: Sopravvivenza | B10: ≤1.5 (Fragile) | C10: Il sub-indice di sopravvivenza è sotto la soglia critica. Ricavi, canali e margini sono le fondamenta di qualsiasi attività — senza queste, il resto non conta. La liquidità insufficiente, la dipendenza da un solo canale o segmento e la scarsa conoscenza dei margini reali sono i tre fattori che, combinati, creano il rischio più concreto per la continuità del business. Non si tratta di crescere: si tratta di stabilizzare le fondamenta prima che uno shock esterno — e prima o poi arriva — trovi l'attività impreparata. Questo sub-indice ha un gate KO: è la priorità assoluta rispetto a qualsiasi altra area.
A11: Sopravvivenza | B11: ≤2.5 (Vulnerabile) | C11: Il sub-indice di sopravvivenza indica una fragilità che richiede attenzione. Non è una crisi, ma è una situazione che può deteriorarsi rapidamente se si presenta uno shock esterno — una stagione difficile, un cambiamento su una piattaforma, un adempimento normativo imprevisto. Liquidità, diversificazione dei canali e conoscenza reale dei margini sono sotto pressione: è da qui che conviene iniziare, prima di lavorare su qualsiasi altra area. Un'attività con queste fondamenta incomplete è esposta in modo che non sempre si vede finché non si manifesta.
A12: Sopravvivenza | B12: >2.5 (Adeguata) | C12: Il sub-indice di sopravvivenza è in territorio positivo. Ricavi, canali e margini reggono il quotidiano con una certa solidità. Ci sono spazi di miglioramento — in particolare sulla prevedibilità dei flussi di cassa, sulla diversificazione dei canali e sulla conoscenza puntuale dei margini per linea — ma la base è sufficientemente solida da permettere di investire energie anche su altri fronti. Continua a monitorare la liquidità con regolarità: è l'indicatore più affidabile di salute operativa.
A13: Sopravvivenza | B13: >3.5 (Solida) | C13: Il sub-indice di sopravvivenza è forte. Ricavi diversificati, canali diretti attivi, margini noti e liquidità adeguata ti mettono in una posizione strutturalmente vantaggiosa rispetto alla maggior parte delle micro-imprese. Hai costruito la base che permette di affrontare uno shock senza andare in crisi e di pensare alla crescita con la solidità necessaria per sostenerla. Il lavoro adesso è ottimizzare il mix, costruire flussi ricorrenti e usare questa stabilità come leva per investire in modo deliberato.
A14: Liquidità
A15: Liquidità | B15: ≤1.5 (Fragile) | C15: Meno di un mese di copertura delle spese fisse. Questo non è un problema di gestione finanziaria — è un'emergenza strutturale. Qualsiasi shock esterno — una settimana lenta, una spesa imprevista, un pagamento in ritardo — può mettere in difficoltà la continuità dell'attività. L'unica priorità adesso è stabilizzare la cassa: ridurre le spese fisse non essenziali, accelerare gli incassi, identificare le voci che si possono posticipare. Ogni altra decisione aspetta che questo indicatore sia fuori dalla zona critica.
A16: Liquidità | B16: ≤2.5 (Vulnerabile) | C16: La copertura attuale è di circa un mese. Non è ancora una crisi, ma il margine è sottile: uno shock di media entità sarebbe sufficiente a creare difficoltà. Il lavoro da fare è sistematico: accantonare ogni mese una percentuale fissa del fatturato, anche piccola, finché la copertura non raggiunge almeno due mesi. Non si tratta di crescita — si tratta di costruire il buffer che permette di gestire l'imprevisto senza andare in debito.
A17: Liquidità | B17: >2.5 (Adeguata) | C17: Hai due o tre mesi di copertura — un buffer decente che ti dà il tempo di reagire se qualcosa cambia. Il lavoro adesso è mantenerlo e aumentarlo gradualmente: accantonare una quota fissa ogni mese e non toccarla se non in caso di vera emergenza. L'obiettivo è arrivare a tre o più mesi, che è il livello che permette di affrontare una stagione difficile o un cambio normativo senza stress strutturale.
A18: Liquidità | B18: >3.5 (Solida) | C18: Quattro o più mesi di copertura. Questo è un vantaggio reale che la maggior parte delle micro-imprese non ha: la capacità di fare scelte deliberate invece di scelte reattive. Puoi aspettare il momento giusto per un investimento, negoziare da una posizione di forza con fornitori e partner, e attraversare una stagione difficile senza compromettere la struttura. Il lavoro adesso è usare questa solidità in modo strategico — non tenerla ferma come riserva passiva, ma come leva per decisioni che richiedono tempo.
A19: Resilienza operativa
A20: Resilienza operativa | B20: ≤1.5 (Fragile) | C20: L'attività dipende interamente da te e opera in isolamento sostanziale. Se ti fermi — anche solo per una settimana — si ferma tutto. E senza una rete nel territorio che possa supportarti, ogni problema si affronta da soli. Queste due fragilità si rinforzano: un sistema fragile senza rete è un'attività che non può permettersi nessuno shock. La priorità è duplice: scrivi il processo più critico della tua attività su un foglio — tre passaggi, in ordine — e contatta tre operatori del territorio questa settimana.
A21: Resilienza operativa | B21: ≤2.5 (Vulnerabile) | C21: Il sistema regge il ritmo normale ma dipende ancora troppo da te. Ci sono alcune connessioni nel territorio, ma non ancora una rete che lavora anche quando non sei tu a spingerla. Le due fragilità si sommano: un imprevisto operativo coincide spesso con il momento in cui avresti più bisogno della rete per tamponarlo. Il lavoro è parallelo: scrivi una procedura critica al mese, e struttura almeno due collaborazioni attive con accordi chiari su chi manda cosa a chi.
A22: Resilienza operativa | B22: >2.5 (Adeguata) | C22: Hai un sistema che funziona anche quando non sei tu a guidarlo ogni passaggio, e sei parte di un territorio con cui collabori in modo attivo. Queste due solidità si rafforzano: un sistema delegabile ti libera tempo per coltivare la rete, e una rete attiva ti porta risorse quando qualcosa si inceppa. Il lavoro adesso è rendere entrambe le dimensioni più strutturate: completare la delegabilità su tutte le aree critiche e formalizzare almeno alcune collaborazioni chiave.
A23: Resilienza operativa | B23: >3.5 (Solida) | C23: La tua attività funziona senza di te, sei riconosciuto nel territorio e le tue relazioni generano valore in modo sempre più autonomo. Questa è la combinazione più difficile da costruire nelle micro-imprese — e la più rara. La solidità operativa ti permette di investire nel territorio, e il radicamento ti porta informazioni e opportunità che nessun sistema interno può generare da solo. Il passo successivo è usare questa posizione strategicamente: co-progettare con altri operatori, contribuire alle decisioni del territorio, costruire un vantaggio che si auto-rafforza.
A24: Digital Readiness
A25: Digital Readiness | B25: ≤1.5 (Fragile) | C25: L'esposizione digitale è sotto la soglia critica. Strumenti inadeguati, dati dei clienti non protetti, assenza di canali diretti e mancato uso delle informazioni disponibili creano una fragilità che si vede poco finché non diventa un problema concreto: una violazione dei dati, una prenotazione persa a causa di un intermediario, una decisione presa senza le informazioni necessarie. Non serve diventare esperti di tecnologia: servono strumenti di base, usati con metodo. L'impatto di un intervento in quest'area è spesso alto e il costo di ingresso è generalmente basso.
A26: Digital Readiness | B26: ≤2.5 (Vulnerabile) | C26: Hai qualcosa, ma non abbastanza per sfruttare il digitale in modo strutturato, proteggere adeguatamente i dati dei tuoi clienti, costruire canali diretti che riducano la dipendenza dagli intermediari e usare le informazioni disponibili per prendere decisioni migliori. Il gap da colmare non è tecnologico — è di metodo e abitudine. Partire da un backup automatico, un sistema per tracciare i contatti clienti, un canale di prenotazione diretta e una lettura periodica dei dati disponibili è già sufficiente per uscire dalla zona di attenzione.
A27: Digital Readiness | B27: >2.5 (Adeguata) | C27: Usi strumenti digitali con struttura, hai attenzione alla protezione dei dati, stai costruendo canali diretti che riducono la dipendenza dagli intermediari e i dati che hai vengono usati, almeno in parte, per orientare le decisioni. Ci sono aree di miglioramento — in particolare sull'integrazione degli strumenti, sulla solidità del canale diretto e sull'uso sistematico dei dati — ma la base digitale lavora a tuo vantaggio.
A28: Digital Readiness | B28: >3.5 (Solida) | C28: Hai strumenti integrati, dati protetti con attenzione, canali diretti attivi e usi in modo deliberato le informazioni che raccogli per prendere decisioni. Questo ti dà un vantaggio competitivo reale rispetto alla maggioranza delle micro-imprese del territorio: sai cosa funziona, puoi misurarlo e puoi migliorarlo nel tempo. Il passo successivo è costruire canali diretti ancora più solidi e trasformare il patrimonio di dati accumulato in un vantaggio strutturale difficile da replicare.
A29: Compliance e protezione
A30: Compliance e protezione | B30: ≤1.5 (Fragile) | C30: Ci sono gap di compliance significativi su più fronti. Non sapere è rischioso quanto sapere e ignorare: un controllo normativo, un sinistro non coperto o un arretrato fiscale possono generare costi sproporzionati rispetto alle dimensioni dell'attività. La priorità è fare una lista delle criticità note — normative, assicurative, fiscali — e affrontarle in ordine di urgenza. Non tutto va risolto subito, ma tutto deve avere un calendario. Il costo della compliance è fisso e prevedibile; il costo dell'esposizione è imprevedibile e spesso moltiplicatore.
A31: Compliance e protezione | B31: ≤2.5 (Vulnerabile) | C31: La compliance è parziale. Alcune obbligazioni sono gestite, altre no, e la protezione assicurativa è incompleta o poco compresa. Il rischio è asimmetrico: la compliance completa costa relativamente poco, ma un gap costa molto nel momento peggiore. Il lavoro da fare è un check sistematico: conformità normativa (CIN, GDPR, sicurezza), copertura assicurativa (danni, RC, interruzione attività), regolarità fiscale e contributiva. Un'area al mese è sufficiente per arrivare a una situazione solida nel giro di qualche mese.
A32: Compliance e protezione | B32: >2.5 (Adeguata) | C32: Sei sostanzialmente in regola e protetto. I rischi principali sono coperti, gli obblighi sono gestiti e sai dove si trovano le aree aperte. Il lavoro adesso è passare da reattivo a proattivo: seguire i cambiamenti normativi prima che diventino obblighi, rivedere la copertura assicurativa annualmente e verificare che sia ancora adeguata alla situazione attuale. La compliance come abitudine ha un costo basso e un impatto alto sulla tranquillità operativa.
A33: Compliance e protezione | B33: >3.5 (Solida) | C33: La compliance è gestita in modo proattivo e fa parte di come gestisci l'attività — non come obbligo burocratico ma come vantaggio strutturale. Sai cosa è coperto, cosa non lo è, e perché. Questo ti mette in una posizione molto più solida della maggior parte delle micro-imprese quando qualcosa di imprevisto accade: non scopri i gap nel momento peggiore, perché non ci sono. Continua ad aggiornare la tua conoscenza normativa e assicurativa con regolarità.
A34: Capacità di evoluzione
A35: Capacità di evoluzione | B35: ≤1.5 (Fragile) | C35: L'attività si muove principalmente sulla base dell'esperienza accumulata — che è una risorsa preziosa, ma non basta da sola a intercettare quello che sta cambiando intorno. Chi non si adatta e non impara in modo attivo tende a scoprire i cambiamenti quando il margine di manovra si è già ridotto. Non è una questione di competenze — è una questione di abitudine deliberata. La differenza tra chi attraversa i momenti difficili e chi no spesso non è la fortuna: è la disciplina sistematica di ascoltare, testare e cambiare.
A36: Capacità di evoluzione | B36: ≤2.5 (Vulnerabile) | C36: C'è una capacità di adattamento e una certa curiosità, ma entrambe tendono ad attivarsi sotto pressione piuttosto che in anticipo. L'apprendimento è episodico: succede quando c'è tempo, quando capita un'occasione. Il lavoro da fare è costruire due abitudini minime e regolari: una di osservazione — cosa cambiano le aspettative dei clienti, cosa fa meglio il competitor più forte — e una di sperimentazione — almeno una cosa nuova ogni trimestre, anche piccola e a basso costo.
A37: Capacità di evoluzione | B37: >2.5 (Adeguata) | C37: Impari in modo attivo e ti adatti quando il mercato o il contesto lo richiedono. Questa combinazione è più rara di quanto sembri tra le micro-imprese. Il lavoro adesso è renderla più sistematica: costruire un ciclo in cui quello che osservi produce una decisione, quella decisione si misura, e il risultato cambia la prossima iterazione. Chi ha questa disciplina non solo reagisce meglio agli shock — inizia ad anticiparli.
A38: Capacità di evoluzione | B38: >3.5 (Solida) | C38: Hai una cultura dell'evoluzione attiva: anticipi i cambiamenti invece di inseguirli, servi mercati diversi e usi quello che impari per prendere decisioni deliberate. Questo è il livello in cui la volatilità del contesto non è solo un rischio — diventa un vantaggio strutturale rispetto a chi non ha la stessa disciplina. Il passo successivo è condividere questo approccio con chi lavora con te e renderlo una parte strutturale di come l'attività funziona — non un'abitudine personale, ma un metodo collettivo.

Sheet 4_PercAnalisi
A1: SEZIONE 4 — PERCEZIONE E ANALISI | 14 template | Attivato se |gap| ≥ 1.5
A2: Area | B2: Direzione del gap | C2: Testo paragrafo
A3: Percezione > Analisi = ti sentivi meglio di quanto emerge. Percezione < Analisi = stavi sottovalutando la tua solidità.
A4: 1. La tua voce
A5: 1. La tua voce | B5: Percezione > Analisi | C5: Ti sentivi più riconoscibile di quanto l'analisi confermi. Succede spesso: chi conosce profondamente la propria attività tende a dare per scontate cose che per un cliente nuovo non sono affatto evidenti — la storia, i dettagli, il perché si fa quello che si fa in quel modo. Quello che per te è ovvio, per chi ti incontra per la prima volta può essere invisibile. Non è una debolezza nella storia: è una distanza tra quello che senti di comunicare e quello che effettivamente arriva. Il lavoro è rendere esplicito quello che finora è rimasto implicito.
A6: 1. La tua voce | B6: Percezione < Analisi | C6: Stai comunicando meglio di quanto ti riconosca. Probabilmente vedi nitidamente tutto quello che ancora non funziona, senza riuscire a vedere quello che già funziona bene — i clienti che tornano per ragioni precise, le recensioni che descrivono qualcosa di specifico, il passaparola che arriva senza che tu lo abbia cercato. Vale la pena chiedere direttamente a qualcuno di cui ti fidi — un cliente abituale, un collaboratore — perché ti sceglie. Le loro parole sono spesso più chiare e convincenti di quanto riesci a dirti da solo.
A7: 2. I tuoi ricavi
A8: 2. I tuoi ricavi | B8: Percezione > Analisi | C8: Ti sentivi più tranquillo sui ricavi di quanto l'analisi confermi. È una delle distorsioni più comuni: la sensazione di controllo e il controllo reale non sempre coincidono. Quando un'attività funziona, si tende a sottostimare la concentrazione — su un canale, su una stagione, su un tipo di cliente — perché finché non si rompe, non si vede quanto sia centrale. L'analisi non dice che stai sbagliando: dice che c'è un punto di fragilità che vale la pena guardare in faccia prima che diventi urgente. Liquidità e concentrazione dei canali sono spesso i due elementi da controllare per primi.
A9: 2. I tuoi ricavi | B9: Percezione < Analisi | C9: Stai gestendo i tuoi ricavi meglio di quanto ti riconosca. Probabilmente senti il peso dell'incertezza — le stagioni difficili, i mesi di cassa stretta, la dipendenza da qualche canale — più della solidità che hai costruito nel tempo. Chi ha costruito resilienza faticando tende a non vederla come un risultato, ma come la normalità. Riconoscere quello che regge non è autocompiacimento: è la base per decidere dove investire con consapevolezza invece di concentrarsi solo su quello che manca.
A10: 3. I tuoi margini
A11: 3. I tuoi margini | B11: Percezione > Analisi | C11: Ti sentivi più a posto sui numeri di quanto l'analisi confermi. Succede spesso, e non è necessariamente un errore di valutazione: la conoscenza dei numeri tende a fermarsi ai ricavi — quello che entra è visibile — mentre i costi, specialmente quelli indiretti, e soprattutto il valore del proprio tempo, restano fuori dal calcolo. Se non includi quanto vale il tuo lavoro tra i costi reali dell'attività, il margine che vedi è più ottimistico di quello reale. Un calcolo preciso, fatto una volta con serietà, cambia la prospettiva su molte decisioni.
A12: 3. I tuoi margini | B12: Percezione < Analisi | C12: Stai gestendo i tuoi numeri meglio di quanto ti riconosca. Chi lavora molto sulla compliance e sul controllo dei costi sviluppa spesso una sensazione di precarietà rispetto ai numeri — come se ci fosse sempre qualcosa che potrebbe mancare. L'analisi dice che la tua situazione è più solida di come la senti. Vale la pena fermarsi a leggere quello che funziona: non per abbassare la guardia, ma per prendere decisioni di investimento e crescita con la consapevolezza che le fondamenta reggono.
A13: 4. La tua adattabilità
A14: 4. La tua adattabilità | B14: Percezione > Analisi | C14: Ti sentivi più pronto ai cambiamenti di quanto l'analisi confermi. È facile confondere la familiarità con la flessibilità: conoscere bene il proprio contesto, sapere come funziona il territorio, avere anni di esperienza — tutto questo dà una sensazione di controllo che non sempre corrisponde alla capacità di rispondere a qualcosa di genuinamente nuovo o imprevisto. La domanda non è se conosci il tuo mercato: è se hai un piano nel caso in cui quel mercato cambi. E se sai già a chi ti rivolgeresti se i tuoi clienti abituali non ci fossero più.
A15: 4. La tua adattabilità | B15: Percezione < Analisi | C15: Hai più flessibilità di quanto ti riconosca. Probabilmente stai misurando la tua adattabilità rispetto a un ideale molto alto — quello dell'imprenditore che anticipa tutto — senza vedere i cambiamenti concreti che hai già fatto: un servizio modificato dopo un feedback, un'offerta nuova per un segmento che non servivi, una risposta efficace a un imprevisto. Tutto questo conta. Capire cosa ha funzionato in passato, e perché, è il modo più affidabile per replicarlo con intenzione.
A16: 5. Il tuo sistema
A17: 5. Il tuo sistema | B17: Percezione > Analisi | C17: Ti sentivi più autonomo di quanto l'analisi confermi. È una delle aree più difficili da valutare dall'interno: chi gestisce un'attività conosce ogni meccanismo e lo attiva in modo automatico, senza accorgersi che quel sapere è interamente nella sua testa e non è mai stato trasferito a nessun altro. Finché sei presente e in forma, il sistema funziona. Ma se ti fermi — per una malattia, un imprevisto, una scelta — non c'è niente che lo sorregga al posto tuo. La dipendenza personale non è un difetto di carattere: è una lacuna strutturale, e si risolve con procedure e delega, non con più impegno.
A18: 5. Il tuo sistema | B18: Percezione < Analisi | C18: Hai più sistema di quanto ti riconosca. Probabilmente vedi con chiarezza le procedure che mancano, i backup che non hai fatto, le cose che ancora dipendono solo da te — e tendi a classificare quello che già funziona come normale, non come un risultato. Ma ogni strumento attivo, ogni persona che sa fare qualcosa al posto tuo, ogni dato organizzato è già sistema. Vale la pena mappare quello che c'è prima di concentrarsi su quello che manca: spesso la distanza da un sistema solido è più corta di quanto sembri.
A19: 6. Le tue radici
A20: 6. Le tue radici | B20: Percezione > Analisi | C20: Ti sentivi più connesso al territorio di quanto l'analisi confermi. La familiarità con i luoghi e le persone può sembrare rete anche quando non lo è ancora nella sostanza. Conoscere i nomi, scambiare qualche parola, avere rapporti cordiali con i vicini — tutto questo è un punto di partenza, non un punto di arrivo. Una rete operativa è qualcosa di diverso: è fatta di scambi concreti, di clienti che si mandano a vicenda, di informazioni che circolano, di collaborazioni con un accordo — anche solo verbale — su chi fa cosa per chi.
A21: 6. Le tue radici | B21: Percezione < Analisi | C21: Sei più radicato di quanto ti riconosca. Probabilmente dai per scontate relazioni e collaborazioni che per molti operatori in aree simili non esistono affatto. Il passaparola che arriva senza che tu lo abbia cercato, i clienti mandati da altri, la reputazione nel territorio — sono tutte forme di capitale relazionale che hai costruito nel tempo. Una rete che non viene vista tende a non essere coltivata: e una rete non coltivata si indebolisce lentamente. Riconoscerla è il primo passo per investirci con consapevolezza.
A22: 7. Il tuo apprendimento
A23: 7. Il tuo apprendimento | B23: Percezione > Analisi | C23: Ti sentivi più aggiornato di quanto l'analisi confermi. È una delle confusioni più frequenti: l'esperienza accumulata è una risorsa preziosa, ma non sempre si aggiorna in modo sistematico. Chi lavora da anni nel proprio settore sa moltissimo — ma tende a imparare per osmosi, non per scelta deliberata. La differenza non è quanto sai: è se hai un canale attivo per raccogliere segnali nuovi, confrontarti con chi fa cose diverse e testare ipotesi in modo intenzionale. Senza un canale deliberato, l'apprendimento rallenta senza che ce ne si accorga.
A24: 7. Il tuo apprendimento | B24: Percezione < Analisi | C24: Stai imparando più di quanto ti riconosca. Probabilmente non stai contando come apprendimento le cose che fai in modo naturale — leggere le recensioni con attenzione, cambiare qualcosa che non funzionava dopo averci ragionato, osservare cosa fanno meglio gli altri e portarne a casa qualcosa di concreto. Tutto questo conta, anche se non ha il formato di un corso o di una certificazione. Il rischio non è l'assenza di apprendimento — è la mancanza di sistematicità: quello che si impara per caso non sempre viene trasformato in un cambiamento intenzionale.

Sheet 5_RischioInerzia
A1: SEZIONE 5 — RISCHIO DI INERZIA | 7 aree × 5 livelli | Scala 1-5
A2: Area | B2: Banda | C2: Testo
A3: Soglie: ≤2.25 | <3.00 | <3.50 | <4.00 | ≤5.00 — Selezione: IF(score≤2.25,C_r1,IF(score<3,C_r2,IF(score<3.5,C_r3,IF(score<4,C_r4,C_r5))))
A4: 1. La tua voce | B4: ≤2.25 | C4: Chi non riesce a capire perché sceglierti tende a decidere in base al prezzo o alla posizione — i due criteri su cui è più difficile competere per una piccola impresa. Ogni giorno senza un posizionamento chiaro è un giorno in cui qualcun altro riempie quello spazio. Non è necessariamente un competitor diretto: a volte è semplicemente la mancanza di un motivo per ricordarti.
A5: 1. La tua voce | B5: <3.00 | C5: Il posizionamento c'è, ma non è ancora abbastanza solido da lavorare per te in modo autonomo. I clienti giusti arrivano, ma non sempre per le ragioni giuste. Il rischio di restare qui — né confuso né riconoscibile — è che il mercato ti classifichi da solo, spesso in modo che non corrisponde a quello che sei davvero.
A6: 1. La tua voce | B6: <3.50 | C6: Hai un'identità sufficientemente chiara da funzionare. Il rischio non è la debolezza — è la deriva silenziosa. Un'identità che non viene curata e aggiornata quando l'offerta evolve tende ad affievolirsi lentamente, senza che ci si accorga, finché ci si rende conto che il messaggio non corrisponde più a quello che si è diventati.
A7: 1. La tua voce | B7: <4.00 | C7: Il tuo posizionamento è solido e riconoscibile. Il lavoro adesso non è costruire — è presidiare. Le identità forti non si erodono di colpo: si erodono per accumulo di piccole incoerenze — un canale trascurato, un messaggio che non si aggiorna, una collaborazione che racconta qualcosa di diverso da quello che sei.
A8: 1. La tua voce | B8: ≤5.00 | C8: Sei in una posizione vantaggiosa: i clienti ti scelgono consapevolmente e sanno spiegarlo. Il rischio a questo livello non è la fragilità — è la compiacenza. Un posizionamento forte non si mantiene da solo nel tempo: richiede cura attiva, aggiornamento quando il contesto cambia e presidio costante della coerenza su tutti i punti di contatto.
A9: 2. I tuoi ricavi | B9: ≤2.25 | C9: Un cambio di algoritmo, una stagione anomala, un canale che cambia le condizioni: questi non sono scenari rari — sono statistiche. La causa principale di chiusura delle piccole imprese non è la mancanza di clienti: è la cassa che non regge un momento difficile. Restare qui senza intervenire significa scommettere che nessuno di questi scenari si materializzerà — e la probabilità che uno si materializzi aumenta con il tempo.
A10: 2. I tuoi ricavi | B10: <3.00 | C10: La struttura dei ricavi regge, ma con margini di tolleranza stretti. Non c'è ancora la diversificazione o la prevedibilità che permettono di affrontare uno shock senza entrare in modalità emergenza. Restare qui a lungo — con la sensazione che tutto sommato funzioni — è esattamente il momento in cui si tende a non fare nulla, e in cui la fragilità rimane senza che se ne abbia piena consapevolezza.
A11: 2. I tuoi ricavi | B11: <3.50 | C11: Hai una base di ricavi che regge il quotidiano. Il rischio è ottimizzare solo quello che già funziona senza costruire la ridondanza che serve quando qualcosa cambia. Chi ha ricavi sufficienti spesso rimanda la diversificazione perché non ne sente l'urgenza — ma la diversificazione si costruisce con calma, non sotto pressione.
A12: 2. I tuoi ricavi | B12: <4.00 | C12: La struttura dei tuoi ricavi è solida. Il passo successivo è trasformare la solidità in prevedibilità: costruire flussi ricorrenti, relazioni dirette con i clienti che riducano la dipendenza dall'acquisizione continua, e un mix che non dipenda interamente da una singola stagione o un singolo canale.
A13: 2. I tuoi ricavi | B13: ≤5.00 | C13: Hai ricavi diversificati, diretti e distribuiti nell'anno. Il lavoro adesso è documentare e proteggere questa struttura: capire esattamente cosa la sostiene, quali scelte l'hanno costruita e come si mantiene nel tempo — perché quello che funziona bene tende a essere dato per scontato fino a quando smette di funzionare.
A14: 3. I tuoi margini | B14: ≤2.25 | C14: Lavorare senza sapere quanto resta davvero — dopo tutte le spese, incluso il valore del proprio tempo — significa prendere decisioni importanti senza le informazioni che servono. Si può lavorare a margine negativo senza accorgersene per mesi. Il costo dell'improvvisazione sui numeri si accumula silenziosamente e arriva in forma di crisi in momenti già difficili.
A15: 3. I tuoi margini | B15: <3.00 | C15: Hai una conoscenza parziale dei tuoi numeri. Sai grossomodo dove stai, ma non con la precisione che serve per fare scelte deliberate su pricing, costi e investimenti. Restare qui — con una visione abbastanza chiara da non preoccuparsi, ma non abbastanza precisa da decidere bene — è il livello in cui si prendono le decisioni più costose senza rendersene conto.
... A38: 7. Il tuo apprendimento | B38: ≤5.00 | C38: Hai una cultura dell'apprendimento solida e strutturata. Ogni ciclo cambia qualcosa in base a quello che hai osservato, testato, imparato — e non stai solo reagendo al mercato, ma contribuendo a interpretarlo. Il rischio a questo livello è diventare così sistematici da perdere la fluidità: l'apprendimento funziona meglio quando combina disciplina e apertura all'imprevisto.

Sheet 6_Azioni
A1: SEZIONE 6 — AZIONI PRIORITARIE | 7 aree × 5 livelli | Scala 1–5
A2: Area | B2: Livello / Priorità | C2: Azione
A3: Soglie: ≤2.25 Urgente | <3.00 Alta | <3.50 Media | <4.00 Bassa | ≤5.00 Mantenimento e sviluppo | Formula selezione: =IF(B<=2.25,C_r1,IF(B<3,C_r2,IF(B<3.5,C_r3,IF(B<4,C_r4,C_r5))))
A4: 1. La tua voce | B4: ≤2.25 (Urgente) | C4: Scrivi in meno di 30 secondi cosa ti rende diverso — non una descrizione di quello che fai, ma la risposta alla domanda: perché dovrei scegliere te invece di qualcun altro? Non pensarci troppo: scrivi la prima cosa che viene. Se non riesci a scriverla in modo convincente, questo è il problema da cui partire — prima di qualsiasi strumento, piattaforma o investimento in comunicazione. Poi prendi quella frase e mostrala a tre clienti di fiducia — quelli che ti scelgono da più tempo e che ti hanno mandato altri clienti. Chiedi loro: "Riconosci la tua esperienza con me in queste parole?" Se non la riconoscono, siediti con loro e riscrivila usando le loro parole, non le tue. Le parole dei clienti sono quasi sempre più precise, più oneste e più convincenti di quelle che userebbe il titolare per descriversi. Poi confronta quello che hai scritto con quello che dice il tuo sito, il tuo profilo sui social, il modo in cui rispondi alle recensioni. Sembrano la stessa attività? Se c'è distanza tra quello che pensi di essere e quello che comunichi, il lavoro inizia da lì — non da nuove foto o nuovi post.
A5: 1. La tua voce | B5: <3.00 (Alta) | C5: Hai qualcosa da raccontare — ma non arriva ancora con la coerenza e la chiarezza che meriterebbe. Il problema non è l'assenza di storia: è che non è ancora stata resa esplicita, strutturata e comunicata in modo che arrivi uguale a chiunque entri in contatto con la tua attività. Il lavoro da fare è in tre passaggi. Primo: chiedi a cinque clienti — quelli che preferisci, quelli che tornan o, quelli che ti mandano altri — perché ti scelgono. Non chiederlo in modo generico: chiedi cosa avrebbero perso se avessero scelto qualcun altro. Le loro risposte ti diranno cosa conta davvero. Secondo: scrivi tre frasi su chi sei, perché sei qui e cosa offri che altri non possono replicare facilmente. Non devono essere perfette — devono essere oneste. Terzo: porta quelle frasi su ogni canale dove sei presente — sito, social, risposta alle prenotazioni, presentazione verbale — e verifica che il tono sia coerente. Non serve una strategia di comunicazione complessa. Serve che chi entra in contatto con te per la prima volta riceva lo stesso messaggio di chi ti conosce da anni.
A6: 1. La tua voce | B6: <3.50 (Media) | C6: La tua identità è chiara per chi ti conosce, ma non è ancora strutturata in modo da lavorare per te in modo autonomo — anche quando non sei tu a presentarti direttamente. Il lavoro adesso è triplice. Primo, fai un audit di coerenza: prendi dieci minuti e controlla il tuo sito, il tuo profilo Google, l'ultima pagina social attiva e le ultime cinque risposte alle recensioni. Il messaggio è lo stesso? Il tono è riconoscibile? Secondo, aggiorna il messaggio se l'offerta è cambiata nell'ultimo anno — le identità scivolano quando l'attività evolve senza che il racconto si aggiorni. Terzo, assicurati che chi lavora o collabora con te sappia come presentare l'attività con le stesse parole che useresti tu: un collaboratore che descrive la tua attività in modo diverso da come la descrivi tu crea confusione anche quando lavora bene. In parallelo, inizia a raccogliere sistematicamente le frasi con cui i clienti ti descrivono nelle recensioni e nel passaparola. Sono il tuo archivio di posizionamento: usale in modo deliberato, non lasciarle sparire.
A7: 1. La tua voce | B7: <4.00 (Bassa) | C7: Sai chi sei e lo comunichi con precisione. Il posizionamento lavora per te: i clienti ti scelgono per ragioni che sanno spiegare, il passaparola funziona e non devi competere solo sul prezzo o sulla posizione. Questo è un asset raro che vale la pena proteggere con la stessa cura con cui è stato costruito. Il lavoro adesso è su due fronti. Il primo è la documentazione: scrivi il tuo posizionamento in modo esplicito — chi sei, per chi, perché, cosa ti rende diverso — in un documento che possa essere condiviso con collaboratori, partner e chiunque parli di te in tua assenza. Un posizionamento che esiste solo nella tua testa è fragile. Il secondo fronte è la raccolta sistematica delle parole dei clienti: le loro recensioni, le frasi che usano quando ti raccomandano, i motivi che danno quando tornano. Questo materiale è il tuo posizionamento visto dall'esterno — è spesso più preciso e convincente di qualsiasi cosa tu scriva su te stesso. Pianifica un check semestrale: l'offerta è cambiata? Il messaggio si è aggiornato? Chi collabora con te racconta la stessa storia?
A8: 1. La tua voce | B8: ≤5.00 (Mantenimento e sviluppo) | C8: Il tuo posizionamento è forte, riconoscibile e coerente. I clienti ti scelgono consapevolmente, sanno spiegarlo e tendono a mandare altri clienti con le stesse caratteristiche — il che significa che il posizionamento non solo attrae, ma filtra. Questa è una condizione strutturalmente vantaggiosa che richiede manutenzione attiva, non solo conservazione passiva. Il lavoro si articola su tre livelli. Il primo è il presidio della coerenza: verifica ogni sei mesi che tutti i punti di contatto — sito, social, risposta alle prenotazioni, presentazione verbale di collaboratori e partner — raccontino la stessa storia. Le identità forti si erodono per accumulo di piccole incoerenze, non di colpo. Il secondo è l'aggiornamento: quando l'offerta evolve, il posizionamento deve evolvere con essa. Non aspettare che la distanza diventi evidente ai clienti prima di correggerla. Il terzo è la capitalizzazione: costruisci un archivio attivo di testimonianze, storie di clienti e materiali che raccontino cosa sei con le parole di chi ti ha scelto — non con le tue. Questo archivio è il tuo posizionamento esternalizzato: funziona anche quando non sei tu a parlare.
A9: 2. I tuoi ricavi | B9: ≤2.25 (Urgente) | C9: Fai una cosa questa settimana, prima di qualsiasi altra decisione: calcola quanti mesi di spese fisse potresti coprire se i ricavi si azzerassero oggi. Non una stima — il numero preciso. Prendi tutte le uscite fisse mensili (affitto o mutuo, utenze, abbonamenti, contributi, eventuali dipendenti o collaboratori fissi) e dividile per la liquidità disponibile. Quel numero è il tuo margine reale di sicurezza. Poi guarda il canale che ti porta la maggior parte dei ricavi — il principale intermediario, la principale tipologia di cliente, il principale periodo dell'anno. Chiediti: se quel canale cambiasse le condizioni domani, o se quel periodo fosse compromesso da un evento esterno, quanto tempo avresti per reagire prima di andare in difficoltà? Questi due numeri non servono a spaventare: servono a rendere visibile il rischio concreto su cui lavorare. L'azione prioritaria è costruire una riserva minima — anche piccola, anche graduale: accantonare il 5-10% di ogni incasso in un conto separato, intoccabile se non per vera emergenza. In parallelo, identifica un secondo canale o un secondo segmento di clienti su cui iniziare a lavorare, anche in piccolo, anche in modo sperimentale.
A10: 2. I tuoi ricavi | B10: <3.00 (Alta) | C10: Hai una base di partenza, ma c'è una concentrazione — su un canale, una stagione, un tipo di cliente — che vale la pena ridurre con metodo prima che si trasformi in un problema. Il primo passo è la diagnosi precisa: calcola quanta parte dei tuoi ricavi annuali viene da un singolo canale, da un singolo mese o da un singolo tipo di cliente. Se uno di questi supera il 50%, hai una concentrazione da gestire. Il secondo passo è costruire almeno una fonte alternativa concreta entro i prossimi tre mesi: un secondo canale di prenotazione o vendita attivo, un'offerta specifica per un periodo che oggi non copri (bassa stagione, infrasettimanale, target diverso), o un segmento di clienti che non stai ancora servendo ma che ha senso per la tua attività. In parallelo, costruisci una riserva di liquidità minima: anche solo due mesi di spese fisse in un conto separato cambiano la struttura del rischio in modo significativo — non perché risolva tutto, ma perché ti dà il tempo di reagire senza dover prendere decisioni affrettate sotto pressione. Tieni traccia mensile dei ricavi per canale: non per fare report, ma per vedere subito se un canale sta perdendo peso.
A11: 2. I tuoi ricavi | B11: <3.50 (Media) | C11: La struttura dei ricavi regge il quotidiano e tiene discretamente agli shock stagionali. Non c'è ancora la diversificazione piena che permetterebbe di attraversare una crisi prolungata senza pressione, ma la base funziona. Il lavoro adesso è consolidarla in modo strutturale. Su tre fronti. Il primo è l'ottimizzazione del mix: analizza i tuoi ricavi per canale e per tipologia di cliente e identifica quali generano il margine migliore — non solo il volume maggiore. Spesso il 20% dei clienti genera il 60% del valore netto: sapere chi sono permette di lavorare per attrarne altri simili. Il secondo fronte è la relazione diretta: costruisci o consolida un database di clienti che hai già servito, con la capacità di contattarli direttamente per offerte, aggiornamenti o inviti a tornare. I ricavi da clienti che già ti conoscono costano meno da generare, sono più stabili e tendono a generare passaparola. Il terzo fronte è la prevedibilità: costruisci almeno due mesi di proiezione sui flussi di cassa — non come esercizio contabile, ma come strumento di decisione. Chi sa a novembre come andrà febbraio ha tempo per agire; chi lo scopre a gennaio spesso no.
A12: 2. I tuoi ricavi | B12: <4.00 (Bassa) | C12: Hai una struttura dei ricavi solida. Il passo successivo è trasformare la solidità in prevedibilità e la prevedibilità in ricorrenza strutturale — cioè ricavi che non dipendono interamente dall'acquisizione continua di nuovi clienti. Il lavoro si articola su due priorità. La prima è la ricorrenza: identifica i clienti che tornano con regolarità e capisci cosa li fa tornare. Poi progetta offerte o format pensati specificamente per loro — abbonamenti, pacchetti stagionali, accesso prioritario, condizioni riservate. Ogni cliente che torna è un cliente che non devi riacquisire. La seconda priorità è la distribuzione dell'anno: se hai ancora mesi significativamente più deboli degli altri, lavora su offerte specifiche per quei periodi — non necessariamente con prezzi più bassi, ma con proposte costruite sulle caratteristiche di quel periodo e sui clienti che lo frequentano. Infine, mantieni aggiornato un cruscotto mensile semplice: ricavi per canale, ricavi da clienti nuovi vs ricavi da clienti di ritorno, liquidità disponibile. Non serve essere commercialisti — serve leggere tre numeri una volta al mese.
A13: 2. I tuoi ricavi | B13: ≤5.00 (Mantenimento e sviluppo) | C13: Hai ricavi diversificati, distribuiti nell'anno e costruiti su più canali. Hai già fatto il lavoro più difficile — costruire resilienza prima che fosse necessaria. Adesso il rischio principale non è la fragilità: è la deriva silenziosa, cioè il progressivo spostamento del peso verso un canale o un periodo senza che ce ne si accorga. Il lavoro di manutenzione si articola su tre livelli. Il primo è il monitoraggio attivo: ogni trimestre, calcola la distribuzione percentuale dei ricavi per canale e per periodo. Se un canale sta crescendo oltre il 40% del totale, è il momento di considerare se è una scelta deliberata o un drift da correggere. Il secondo livello è la documentazione del modello: scrivi in modo esplicito le scelte che hai fatto — quali canali presidii, con quale logica, come hai distribuito l'anno, qual è la tua riserva target. Questo documento serve a te nei momenti di decisione e a chiunque ti affianchi in futuro. Il terzo livello è l'ottimizzazione: con una struttura stabile puoi permetterti di ottimizzare il mix — ridurre la dipendenza dai canali a margine più basso, aumentare la quota diretta, costruire flussi ricorrenti più solidi.
A14: 3. I tuoi margini | B14: ≤2.25 (Urgente) | C14: Prendi l'ultimo mese e calcola il margine netto reale — non il fatturato, non il lordo, ma quello che resta dopo tutte le spese. Fallo in modo completo: tutte le uscite fisse (affitto o mutuo, utenze, abbonamenti, software, assicurazioni, contributi), tutte le uscite variabili (fornitori, materiali, commissioni sulle prenotazioni, eventuali collaboratori a progetto), e — voce che viene quasi sempre dimenticata — il valore delle ore che hai lavorato tu. Su quest'ultimo punto: se dovessi pagare qualcuno per fare quello che fai tu, quanto gli daresti al mese? Scrivi quel numero. Aggiungilo ai costi. Quello che resta è il tuo margine reale — non quello percepito. Se il risultato ti sorprende, è meglio saperlo adesso che quando non c'è più spazio per correggere la rotta. L'azione immediata è due cose in parallelo: primo, inizia a tracciare le spese in modo sistematico — anche solo su un foglio Excel con le categorie principali, aggiornato ogni settimana. Secondo, verifica la tua situazione fiscale e contributiva: sai quali scadenze ti aspettano nei prossimi sei mesi? Sai quanto stai accantonando? Molte crisi di liquidità nelle micro-imprese non vengono da ricavi insufficienti — vengono da scadenze fiscali che arrivano quando la cassa è già bassa.
A15: 3. I tuoi margini | B15: <3.00 (Alta) | C15: Hai una conoscenza parziale dei tuoi numeri — abbastanza da gestire il quotidiano, non abbastanza da fare scelte deliberate su pricing, investimenti e struttura dei costi. Il lavoro si articola su quattro aree. Prima: struttura il tracciamento delle spese in modo sistematico. Non serve un software contabile — basta un foglio con le categorie principali aggiornato settimanalmente. Il punto è avere una lettura mensile precisa che includa tutte le voci, incluso il valore del tuo lavoro. Seconda: calcola il break-even della tua attività — quanti euro di fatturato ti servono al mese per coprire tutte le spese, incluse quelle che paghi una volta all'anno (assicurazioni, tasse, manutenzioni). Sapere questo numero cambia il modo in cui valuti ogni mese. Terza: verifica la compliance sugli adempimenti principali — CIN se applicabile, GDPR per i dati clienti, scadenze fiscali e contributive. Non sapere ha un costo che tende a presentarsi nel momento peggiore. Quarta: controlla se la tua copertura assicurativa è adeguata per quello che fai davvero — non per quello che facevi quando l'hai stipulata.
... A38: 7. Il tuo apprendimento | B38: ≤5.00 (Mantenimento e sviluppo) | C38: Hai una cultura dell'apprendimento attiva e strutturata. Ogni ciclo cambia qualcosa in base a quello che hai osservato, testato, imparato. Non stai solo reagendo al mercato — stai contribuendo a interpretarlo prima degli altri. Questa capacità è uno degli asset più difficili da costruire e più facili da perdere se non viene mantenuta con la stessa disciplina con cui è stata sviluppata. Il lavoro di manutenzione ha quattro dimensioni. La prima è la continuità della pratica: mantieni le abitudini di osservazione anche nei periodi in cui tutto va bene e non c'è pressione esterna a stimolarlo. Chi smette di guardare quando è in forma è il primo a essere sorpreso quando qualcosa cambia. La seconda dimensione è la documentazione: trascrivi quello che impari in modo che non rimanga solo nella tua testa — un documento di apprendimento annuale, anche informale, che raccoglie cosa hai cambiato, perché e con che risultato. La terza è la condivisione: contribuisci attivamente alla conoscenza collettiva del tuo settore e del tuo territorio — in reti di operatori, in eventi, in conversazioni con colleghi. Chi insegna impara due volte. La quarta è l'evoluzione del metodo stesso: ogni anno, rivedi come stai imparando. Il sistema di apprendimento che funzionava tre anni fa potrebbe aver bisogno di un aggiornamento.
